{"nam":"Engine","dat":[{"nam":"GameSpace","dat":[{"objID":1622,"componentArray":[{"nam":"ObjectInfo","dat":{"savesWithLevel":{"nam":"bool","dat":true},"id":{"nam":"int","dat":1622},"tags":{"nam":"TagMap","dat":{"Player":3563643746}},"name":{"nam":"std::string","dat":"StoneGnome"},"destroyed":{"nam":"bool","dat":false},"active":{"nam":"bool","dat":true}}},{"nam":"TransformComponent","dat":{"position":{"nam":"vec2","dat":{"x":{"nam":"float","dat":-4.71173095703125},"y":{"nam":"float","dat":-86066768.0}}},"scale":{"nam":"vec3","dat":{"x":{"nam":"float","dat":1.0},"y":{"nam":"float","dat":1.0},"z":{"nam":"float","dat":1.0}}},"zLayer":{"nam":"float","dat":-1.0},"rotation":{"nam":"float","dat":22.176660537719728},"parent":{"nam":"GameObject","dat":{"id":{"nam":"int","dat":0}}}}},{"nam":"RigidBodyComponent","dat":{"gravity":{"nam":"vec3","dat":{"x":{"nam":"float","dat":0.0},"y":{"nam":"float","dat":-9.0},"z":{"nam":"float","dat":0.0}}},"acceleration":{"nam":"vec3","dat":{"x":{"nam":"float","dat":0.0},"y":{"nam":"float","dat":0.0},"z":{"nam":"float","dat":0.0}}},"velocity":{"nam":"vec3","dat":{"x":{"nam":"float","dat":0.0},"y":{"nam":"float","dat":-39369.66796875},"z":{"nam":"float","dat":0.0}}},"mass":{"nam":"float","dat":0.0}}},{"nam":"SpriteComponent","dat":{"id":{"nam":"unsigned long long","dat":3032232252},"textureHandler":{"nam":"TextureHandler","dat":{"timer":{"nam":"float","dat":2531.73779296875},"isTiling":{"nam":"bool","dat":false},"tileAmount":{"nam":"vec2","dat":{"x":{"nam":"float","dat":1.0},"y":{"nam":"float","dat":1.0}}},"isAnimated":{"nam":"bool","dat":true},"currentFrame":{"nam":"int","dat":0},"id":{"nam":"unsigned long long","dat":3032232252},"fps":{"nam":"float","dat":0.0}}},"color":{"nam":"glm::vec4","dat":{"x":{"nam":"float","dat":0.04052014276385307},"y":{"nam":"float","dat":0.039381708949804309},"z":{"nam":"float","dat":0.041379332542419437},"w":{"nam":"float","dat":1.0}}}}}]},{"objID":1614,"componentArray":[{"nam":"ObjectInfo","dat":{"savesWithLevel":{"nam":"bool","dat":true},"id":{"nam":"int","dat":1614},"tags":{"nam":"TagMap","dat":{}},"name":{"nam":"std::string","dat":"Tree5"},"destroyed":{"nam":"bool","dat":false},"active":{"nam":"bool","dat":true}}},{"nam":"TransformComponent","dat":{"position":{"nam":"vec2","dat":{"x":{"nam":"float","dat":8.059438705444336},"y":{"nam":"float","dat":-8.977741241455079}}},"scale":{"nam":"vec3","dat":{"x":{"nam":"float","dat":1.8500001430511475},"y":{"nam":"float","dat":2.7800002098083498},"z":{"nam":"float","dat":1.0}}},"zLayer":{"nam":"float","dat":-1.0},"rotation":{"nam":"float","dat":0.0},"parent":{"nam":"GameObject","dat":{"id":{"nam":"int","dat":0}}}}},{"nam":"SpriteComponent","dat":{"id":{"nam":"unsigned long long","dat":2597234851},"textureHandler":{"nam":"TextureHandler","dat":{"timer":{"nam":"float","dat":0.0},"isTiling":{"nam":"bool","dat":false},"tileAmount":{"nam":"vec2","dat":{"x":{"nam":"float","dat":1.0},"y":{"nam":"float","dat":1.0}}},"isAnimated":{"nam":"bool","dat":false},"currentFrame":{"nam":"int","dat":0},"id":{"nam":"unsigned long long","dat":2597234851},"fps":{"nam":"float","dat":0.0}}},"color":{"nam":"glm::vec4","dat":{"x":{"nam":"float","dat":1.0},"y":{"nam":"float","dat":1.0},"z":{"nam":"float","dat":1.0},"w":{"nam":"float","dat":1.0}}}}}]},{"objID":1615,"componentArray":[{"nam":"ObjectInfo","dat":{"savesWithLevel":{"nam":"bool","dat":true},"id":{"nam":"int","dat":1615},"tags":{"nam":"TagMap","dat":{}},"name":{"nam":"std::string","dat":"Tree4"},"destroyed":{"nam":"bool","dat":false},"active":{"nam":"bool","dat":true}}},{"nam":"TransformComponent","dat":{"position":{"nam":"vec2","dat":{"x":{"nam":"float","dat":7.12461519241333},"y":{"nam":"float","dat":-15.699146270751954}}},"scale":{"nam":"vec3","dat":{"x":{"nam":"float","dat":5.773750305175781},"y":{"nam":"float","dat":5.773750305175781},"z":{"nam":"float","dat":1.0}}},"zLayer":{"nam":"float","dat":-2.0},"rotation":{"nam":"float","dat":0.0},"parent":{"nam":"GameObject","dat":{"id":{"nam":"int","dat":0}}}}},{"nam":"SpriteComponent","dat":{"id":{"nam":"unsigned long long","dat":4079660110},"textureHandler":{"nam":"TextureHandler","dat":{"timer":{"nam":"float","dat":0.0},"isTiling":{"nam":"bool","dat":false},"tileAmount":{"nam":"vec2","dat":{"x":{"nam":"float","dat":1.0},"y":{"nam":"float","dat":1.0}}},"isAnimated":{"nam":"bool","dat":false},"currentFrame":{"nam":"int","dat":0},"id":{"nam":"unsigned long long","dat":4079660110},"fps":{"nam":"float","dat":0.0}}},"color":{"nam":"glm::vec4","dat":{"x":{"nam":"float","dat":1.0},"y":{"nam":"float","dat":1.0},"z":{"nam":"float","dat":1.0},"w":{"nam":"float","dat":1.0}}}}}]},{"objID":1616,"componentArray":[{"nam":"ObjectInfo","dat":{"savesWithLevel":{"nam":"bool","dat":true},"id":{"nam":"int","dat":1616},"tags":{"nam":"TagMap","dat":{}},"name":{"nam":"std::string","dat":"Sign"},"destroyed":{"nam":"bool","dat":false},"active":{"nam":"bool","dat":true}}},{"nam":"TransformComponent","dat":{"position":{"nam":"vec2","dat":{"x":{"nam":"float","dat":0.8252101540565491},"y":{"nam":"float","dat":10.364051818847657}}},"scale":{"nam":"vec3","dat":{"x":{"nam":"float","dat":1.0},"y":{"nam":"float","dat":1.0},"z":{"nam":"float","dat":1.0}}},"zLayer":{"nam":"float","dat":0.0},"rotation":{"nam":"float","dat":0.0},"parent":{"nam":"GameObject","dat":{"id":{"nam":"int","dat":0}}}}}]},{"objID":1618,"componentArray":[{"nam":"ObjectInfo","dat":{"savesWithLevel":{"nam":"bool","dat":true},"id":{"nam":"int","dat":1618},"tags":{"nam":"TagMap","dat":{}},"name":{"nam":"std::string","dat":"RedGnomeWeapon"},"destroyed":{"nam":"bool","dat":false},"active":{"nam":"bool","dat":false}}},{"nam":"TransformComponent","dat":{"position":{"nam":"vec2","dat":{"x":{"nam":"float","dat":-7.45913028717041},"y":{"nam":"float","dat":-7.052971839904785}}},"scale":{"nam":"vec3","dat":{"x":{"nam":"float","dat":1.0},"y":{"nam":"float","dat":1.0},"z":{"nam":"float","dat":1.0}}},"zLayer":{"nam":"float","dat":0.0},"rotation":{"nam":"float","dat":70.0},"parent":{"nam":"GameObject","dat":{"id":{"nam":"int","dat":0}}}}},{"nam":"StaticCollider2DComponent","dat":{"colliderData":{"nam":"Collider2D","dat":{"selfElasticity":{"nam":"float","dat":0.0},"colliderShape":{"nam":"int","dat":3},"offset":{"nam":"vec3","dat":{"x":{"nam":"float","dat":0.0},"y":{"nam":"float","dat":0.0},"z":{"nam":"float","dat":0.0}}},"collisionLayer":{"nam":"CollisionLayer","dat":{"layer":{"nam":"int","dat":32}}},"dimensions":{"nam":"vec3","dat":{"x":{"nam":"float","dat":0.5700000524520874},"y":{"nam":"float","dat":0.3700000047683716},"z":{"nam":"float","dat":1.0}}},"rotationOffset":{"nam":"float","dat":0.0},"layersCollidedWith":{"nam":"int","dat":0},"collisionType":{"nam":"collisionType","dat":1},"appliedElasticity":{"nam":"float","dat":0.0}}}}},{"nam":"SpriteComponent","dat":{"id":{"nam":"unsigned long long","dat":1762129289},"textureHandler":{"nam":"TextureHandler","dat":{"timer":{"nam":"float","dat":0.0},"isTiling":{"nam":"bool","dat":false},"tileAmount":{"nam":"vec2","dat":{"x":{"nam":"float","dat":1.0},"y":{"nam":"float","dat":1.0}}},"isAnimated":{"nam":"bool","dat":false},"currentFrame":{"nam":"int","dat":0},"id":{"nam":"unsigned long long","dat":1762129289},"fps":{"nam":"float","dat":0.0}}},"color":{"nam":"glm::vec4","dat":{"x":{"nam":"float","dat":1.0},"y":{"nam":"float","dat":1.0},"z":{"nam":"float","dat":1.0},"w":{"nam":"float","dat":1.0}}}}},{"nam":"ScriptComponent","dat":[{"nam":"LuaScript","dat":{"thisObject":{"nam":"GameObject","dat":{"id":{"nam":"int","dat":1618}}},"resourceID":{"nam":"unsigned long long","dat":17856770},"vars":{"defaultRotation":{"nam":"double","dat":70.0},"DURATION_RESET":{"nam":"double","dat":0.1},"xOFFSET":{"nam":"double","dat":0.5},"duration":{"nam":"double","dat":0.1},"yOFFSET":{"nam":"double","dat":0.1}}}}]}]},{"objID":1619,"componentArray":[{"nam":"ObjectInfo","dat":{"savesWithLevel":{"nam":"bool","dat":true},"id":{"nam":"int","dat":1619},"tags":{"nam":"TagMap","dat":{}},"name":{"nam":"std::string","dat":"Coin"},"destroyed":{"nam":"bool","dat":false},"active":{"nam":"bool","dat":true}}},{"nam":"TransformComponent","dat":{"position":{"nam":"vec2","dat":{"x":{"nam":"float","dat":5101.8359375},"y":{"nam":"float","dat":-20823236.0}}},"scale":{"nam":"vec3","dat":{"x":{"nam":"float","dat":-1.25},"y":{"nam":"float","dat":2.0},"z":{"nam":"float","dat":1.0}}},"zLayer":{"nam":"float","dat":0.0},"rotation":{"nam":"float","dat":0.0},"parent":{"nam":"GameObject","dat":{"id":{"nam":"int","dat":0}}}}},{"nam":"RigidBodyComponent","dat":{"gravity":{"nam":"vec3","dat":{"x":{"nam":"float","dat":0.0},"y":{"nam":"float","dat":-9.0},"z":{"nam":"float","dat":0.0}}},"acceleration":{"nam":"vec3","dat":{"x":{"nam":"float","dat":0.0},"y":{"nam":"float","dat":0.0},"z":{"nam":"float","dat":0.0}}},"velocity":{"nam":"vec3","dat":{"x":{"nam":"float","dat":-2.0},"y":{"nam":"float","dat":-13035.2373046875},"z":{"nam":"float","dat":0.0}}},"mass":{"nam":"float","dat":0.0}}},{"nam":"DynamicCollider2DComponent","dat":{"colliderData":{"nam":"Collider2D","dat":{"selfElasticity":{"nam":"float","dat":0.0},"colliderShape":{"nam":"int","dat":2},"offset":{"nam":"vec3","dat":{"x":{"nam":"float","dat":0.0},"y":{"nam":"float","dat":0.0},"z":{"nam":"float","dat":0.0}}},"collisionLayer":{"nam":"CollisionLayer","dat":{"layer":{"nam":"int","dat":16}}},"dimensions":{"nam":"vec3","dat":{"x":{"nam":"float","dat":1.25},"y":{"nam":"float","dat":2.0},"z":{"nam":"float","dat":1.0}}},"rotationOffset":{"nam":"float","dat":0.0},"layersCollidedWith":{"nam":"int","dat":0},"collisionType":{"nam":"collisionType","dat":0},"appliedElasticity":{"nam":"float","dat":0.0}}}}},{"nam":"SpriteComponent","dat":{"id":{"nam":"unsigned long long","dat":651912714},"textureHandler":{"nam":"TextureHandler","dat":{"timer":{"nam":"float","dat":0.0},"isTiling":{"nam":"bool","dat":false},"tileAmount":{"nam":"vec2","dat":{"x":{"nam":"float","dat":1.0},"y":{"nam":"float","dat":1.0}}},"isAnimated":{"nam":"bool","dat":false},"currentFrame":{"nam":"int","dat":0},"id":{"nam":"unsigned long long","dat":651912714},"fps":{"nam":"float","dat":0.0}}},"color":{"nam":"glm::vec4","dat":{"x":{"nam":"float","dat":1.0},"y":{"nam":"float","dat":1.0},"z":{"nam":"float","dat":1.0},"w":{"nam":"float","dat":1.0}}}}},{"nam":"ScriptComponent","dat":[{"nam":"LuaScript","dat":{"thisObject":{"nam":"GameObject","dat":{"id":{"nam":"int","dat":1619}}},"resourceID":{"nam":"unsigned long long","dat":1476025226},"vars":{"GROUND_LAYER":{"nam":"double","dat":8.0},"DAMAGE_FLASH_TIME":{"nam":"double","dat":0.1},"damageFlashTimer":{"nam":"double","dat":-681.8032272383571},"speed":{"nam":"double","dat":2.0},"ALLY_PROJECTILE_LAYER":{"nam":"double","dat":32.0},"scared":{"nam":"bool","dat":false},"health":{"nam":"double","dat":10.0},"scaredSpeed":{"nam":"double","dat":3.0},"direction":{"nam":"double","dat":-1.0}}}}]}]},{"objID":1620,"componentArray":[{"nam":"ObjectInfo","dat":{"savesWithLevel":{"nam":"bool","dat":true},"id":{"nam":"int","dat":1620},"tags":{"nam":"TagMap","dat":{}},"name":{"nam":"std::string","dat":"Background_Hills"},"destroyed":{"nam":"bool","dat":false},"active":{"nam":"bool","dat":true}}},{"nam":"TransformComponent","dat":{"position":{"nam":"vec2","dat":{"x":{"nam":"float","dat":47.66100311279297},"y":{"nam":"float","dat":-9.57769775390625}}},"scale":{"nam":"vec3","dat":{"x":{"nam":"float","dat":1.0},"y":{"nam":"float","dat":1.0},"z":{"nam":"float","dat":1.0}}},"zLayer":{"nam":"float","dat":-98.0},"rotation":{"nam":"float","dat":0.0},"parent":{"nam":"GameObject","dat":{"id":{"nam":"int","dat":0}}}}},{"nam":"BackgroundComponent","dat":{"resourceID":{"nam":"unsigned long long","dat":59317336},"subTextureSize":{"nam":"vec2","dat":{"x":{"nam":"float","dat":0.4000000059604645},"y":{"nam":"float","dat":2.0}}},"backgroundType":{"nam":"int","dat":2},"parallaxBounds":{"nam":"glm::vec4","dat":{"x":{"nam":"float","dat":8.0},"y":{"nam":"float","dat":0.0},"z":{"nam":"float","dat":100.00000762939453},"w":{"nam":"float","dat":100.0}}},"subTexturePosition":{"nam":"vec2","dat":{"x":{"nam":"float","dat":0.0},"y":{"nam":"float","dat":0.0}}},"textureXRange":{"nam":"vec2","dat":{"x":{"nam":"float","dat":0.0},"y":{"nam":"float","dat":1.0}}},"textureYRange":{"nam":"vec2","dat":{"x":{"nam":"float","dat":1.0},"y":{"nam":"float","dat":0.0}}}}}]},{"objID":1621,"componentArray":[{"nam":"ObjectInfo","dat":{"savesWithLevel":{"nam":"bool","dat":true},"id":{"nam":"int","dat":1621},"tags":{"nam":"TagMap","dat":{}},"name":{"nam":"std::string","dat":"Tree1"},"destroyed":{"nam":"bool","dat":false},"active":{"nam":"bool","dat":true}}},{"nam":"TransformComponent","dat":{"position":{"nam":"vec2","dat":{"x":{"nam":"float","dat":-6.545478820800781},"y":{"nam":"float","dat":-9.411208152770996}}},"scale":{"nam":"vec3","dat":{"x":{"nam":"float","dat":2.7860000133514406},"y":{"nam":"float","dat":1.2260000705718995},"z":{"nam":"float","dat":1.0}}},"zLayer":{"nam":"float","dat":-1.0},"rotation":{"nam":"float","dat":0.0},"parent":{"nam":"GameObject","dat":{"id":{"nam":"int","dat":0}}}}},{"nam":"SpriteComponent","dat":{"id":{"nam":"unsigned long long","dat":4245586352},"textureHandler":{"nam":"TextureHandler","dat":{"timer":{"nam":"float","dat":0.0},"isTiling":{"nam":"bool","dat":false},"tileAmount":{"nam":"vec2","dat":{"x":{"nam":"float","dat":1.0},"y":{"nam":"float","dat":1.0}}},"isAnimated":{"nam":"bool","dat":false},"currentFrame":{"nam":"int","dat":0},"id":{"nam":"unsigned long long","dat":4245586352},"fps":{"nam":"float","dat":0.0}}},"color":{"nam":"glm::vec4","dat":{"x":{"nam":"float","dat":1.0},"y":{"nam":"float","dat":1.0},"z":{"nam":"float","dat":1.0},"w":{"nam":"float","dat":1.0}}}}}]},{"objID":1623,"componentArray":[{"nam":"ObjectInfo","dat":{"savesWithLevel":{"nam":"bool","dat":true},"id":{"nam":"int","dat":1623},"tags":{"nam":"TagMap","dat":{"Enemy":2918293704}},"name":{"nam":"std::string","dat":"EnemyShroom"},"destroyed":{"nam":"bool","dat":false},"active":{"nam":"bool","dat":true}}},{"nam":"TransformComponent","dat":{"position":{"nam":"vec2","dat":{"x":{"nam":"float","dat":16.553836822509767},"y":{"nam":"float","dat":-13.052821159362793}}},"scale":{"nam":"vec3","dat":{"x":{"nam":"float","dat":1.25},"y":{"nam":"float","dat":2.0},"z":{"nam":"float","dat":1.0}}},"zLayer":{"nam":"float","dat":0.0},"rotation":{"nam":"float","dat":0.0},"parent":{"nam":"GameObject","dat":{"id":{"nam":"int","dat":0}}}}},{"nam":"RigidBodyComponent","dat":{"gravity":{"nam":"vec3","dat":{"x":{"nam":"float","dat":0.0},"y":{"nam":"float","dat":-9.0},"z":{"nam":"float","dat":0.0}}},"acceleration":{"nam":"vec3","dat":{"x":{"nam":"float","dat":0.0},"y":{"nam":"float","dat":0.0},"z":{"nam":"float","dat":0.0}}},"velocity":{"nam":"vec3","dat":{"x":{"nam":"float","dat":2.0},"y":{"nam":"float","dat":0.0},"z":{"nam":"float","dat":0.0}}},"mass":{"nam":"float","dat":0.0}}},{"nam":"DynamicCollider2DComponent","dat":{"colliderData":{"nam":"Collider2D","dat":{"selfElasticity":{"nam":"float","dat":0.0},"colliderShape":{"nam":"int","dat":2},"offset":{"nam":"vec3","dat":{"x":{"nam":"float","dat":0.0},"y":{"nam":"float","dat":0.0},"z":{"nam":"float","dat":0.0}}},"collisionLayer":{"nam":"CollisionLayer","dat":{"layer":{"nam":"int","dat":16}}},"dimensions":{"nam":"vec3","dat":{"x":{"nam":"float","dat":1.25},"y":{"nam":"float","dat":2.0},"z":{"nam":"float","dat":1.0}}},"rotationOffset":{"nam":"float","dat":0.0},"layersCollidedWith":{"nam":"int","dat":8},"collisionType":{"nam":"collisionType","dat":0},"appliedElasticity":{"nam":"float","dat":0.0}}}}},{"nam":"SpriteComponent","dat":{"id":{"nam":"unsigned long long","dat":651912714},"textureHandler":{"nam":"TextureHandler","dat":{"timer":{"nam":"float","dat":0.0},"isTiling":{"nam":"bool","dat":false},"tileAmount":{"nam":"vec2","dat":{"x":{"nam":"float","dat":1.0},"y":{"nam":"float","dat":1.0}}},"isAnimated":{"nam":"bool","dat":false},"currentFrame":{"nam":"int","dat":0},"id":{"nam":"unsigned long long","dat":651912714},"fps":{"nam":"float","dat":0.0}}},"color":{"nam":"glm::vec4","dat":{"x":{"nam":"float","dat":1.0},"y":{"nam":"float","dat":1.0},"z":{"nam":"float","dat":1.0},"w":{"nam":"float","dat":1.0}}}}},{"nam":"ScriptComponent","dat":[{"nam":"LuaScript","dat":{"thisObject":{"nam":"GameObject","dat":{"id":{"nam":"int","dat":1623}}},"resourceID":{"nam":"unsigned long long","dat":1476025226},"vars":{"GROUND_LAYER":{"nam":"double","dat":8.0},"DAMAGE_FLASH_TIME":{"nam":"double","dat":0.1},"damageFlashTimer":{"nam":"double","dat":-681.8032272383571},"speed":{"nam":"double","dat":2.0},"ALLY_PROJECTILE_LAYER":{"nam":"double","dat":32.0},"scared":{"nam":"bool","dat":false},"health":{"nam":"double","dat":10.0},"scaredSpeed":{"nam":"double","dat":3.0},"direction":{"nam":"double","dat":1.0}}}}]}]},{"objID":1624,"componentArray":[{"nam":"ObjectInfo","dat":{"savesWithLevel":{"nam":"bool","dat":true},"id":{"nam":"int","dat":1624},"tags":{"nam":"TagMap","dat":{"Ground":185762651}},"name":{"nam":"std::string","dat":"Ground"},"destroyed":{"nam":"bool","dat":false},"active":{"nam":"bool","dat":true}}},{"nam":"TransformComponent","dat":{"position":{"nam":"vec2","dat":{"x":{"nam":"float","dat":-12.069263458251954},"y":{"nam":"float","dat":-0.16894784569740296}}},"scale":{"nam":"vec3","dat":{"x":{"nam":"float","dat":30.88397789001465},"y":{"nam":"float","dat":0.5},"z":{"nam":"float","dat":1.0}}},"zLayer":{"nam":"float","dat":0.0},"rotation":{"nam":"float","dat":0.0},"parent":{"nam":"GameObject","dat":{"id":{"nam":"int","dat":0}}}}},{"nam":"StaticCollider2DComponent","dat":{"colliderData":{"nam":"Collider2D","dat":{"selfElasticity":{"nam":"float","dat":0.0},"colliderShape":{"nam":"int","dat":3},"offset":{"nam":"vec3","dat":{"x":{"nam":"float","dat":0.0},"y":{"nam":"float","dat":0.0},"z":{"nam":"float","dat":0.0}}},"collisionLayer":{"nam":"CollisionLayer","dat":{"layer":{"nam":"int","dat":8}}},"dimensions":{"nam":"vec3","dat":{"x":{"nam":"float","dat":30.88397789001465},"y":{"nam":"float","dat":0.5},"z":{"nam":"float","dat":1.0}}},"rotationOffset":{"nam":"float","dat":0.0},"layersCollidedWith":{"nam":"int","dat":1056},"collisionType":{"nam":"collisionType","dat":0},"appliedElasticity":{"nam":"float","dat":0.0}}}}},{"nam":"SpriteComponent","dat":{"id":{"nam":"unsigned long long","dat":4046731729},"textureHandler":{"nam":"TextureHandler","dat":{"timer":{"nam":"float","dat":0.0},"isTiling":{"nam":"bool","dat":true},"tileAmount":{"nam":"vec2","dat":{"x":{"nam":"float","dat":2.0},"y":{"nam":"float","dat":2.0}}},"isAnimated":{"nam":"bool","dat":false},"currentFrame":{"nam":"int","dat":0},"id":{"nam":"unsigned long long","dat":4046731729},"fps":{"nam":"float","dat":0.0}}},"color":{"nam":"glm::vec4","dat":{"x":{"nam":"float","dat":1.0},"y":{"nam":"float","dat":1.0},"z":{"nam":"float","dat":1.0},"w":{"nam":"float","dat":1.0}}}}},{"nam":"HierarchyComponent","dat":{}}]},{"objID":1625,"componentArray":[{"nam":"ObjectInfo","dat":{"savesWithLevel":{"nam":"bool","dat":true},"id":{"nam":"int","dat":1625},"tags":{"nam":"TagMap","dat":{}},"name":{"nam":"std::string","dat":"Ground"},"destroyed":{"nam":"bool","dat":false},"active":{"nam":"bool","dat":true}}},{"nam":"TransformComponent","dat":{"position":{"nam":"vec2","dat":{"x":{"nam":"float","dat":21.463768005371095},"y":{"nam":"float","dat":-15.190937995910645}}},"scale":{"nam":"vec3","dat":{"x":{"nam":"float","dat":13.028411865234375},"y":{"nam":"float","dat":2.276233673095703},"z":{"nam":"float","dat":1.0}}},"zLayer":{"nam":"float","dat":0.0},"rotation":{"nam":"float","dat":0.0},"parent":{"nam":"GameObject","dat":{"id":{"nam":"int","dat":0}}}}},{"nam":"StaticCollider2DComponent","dat":{"colliderData":{"nam":"Collider2D","dat":{"selfElasticity":{"nam":"float","dat":0.0},"colliderShape":{"nam":"int","dat":3},"offset":{"nam":"vec3","dat":{"x":{"nam":"float","dat":0.0},"y":{"nam":"float","dat":0.0},"z":{"nam":"float","dat":0.0}}},"collisionLayer":{"nam":"CollisionLayer","dat":{"layer":{"nam":"int","dat":8}}},"dimensions":{"nam":"vec3","dat":{"x":{"nam":"float","dat":13.028411865234375},"y":{"nam":"float","dat":2.276233673095703},"z":{"nam":"float","dat":1.0}}},"rotationOffset":{"nam":"float","dat":0.0},"layersCollidedWith":{"nam":"int","dat":16},"collisionType":{"nam":"collisionType","dat":0},"appliedElasticity":{"nam":"float","dat":0.0}}}}},{"nam":"SpriteComponent","dat":{"id":{"nam":"unsigned long long","dat":709983426},"textureHandler":{"nam":"TextureHandler","dat":{"timer":{"nam":"float","dat":0.0},"isTiling":{"nam":"bool","dat":true},"tileAmount":{"nam":"vec2","dat":{"x":{"nam":"float","dat":2.0},"y":{"nam":"float","dat":2.0}}},"isAnimated":{"nam":"bool","dat":false},"currentFrame":{"nam":"int","dat":0},"id":{"nam":"unsigned long long","dat":709983426},"fps":{"nam":"float","dat":0.0}}},"color":{"nam":"glm::vec4","dat":{"x":{"nam":"float","dat":1.0},"y":{"nam":"float","dat":1.0},"z":{"nam":"float","dat":1.0},"w":{"nam":"float","dat":1.0}}}}}]},{"objID":1626,"componentArray":[{"nam":"ObjectInfo","dat":{"savesWithLevel":{"nam":"bool","dat":true},"id":{"nam":"int","dat":1626},"tags":{"nam":"TagMap","dat":{}},"name":{"nam":"std::string","dat":"Stats"},"destroyed":{"nam":"bool","dat":false},"active":{"nam":"bool","dat":true}}},{"nam":"TransformComponent","dat":{"position":{"nam":"vec2","dat":{"x":{"nam":"float","dat":0.7829840183258057},"y":{"nam":"float","dat":-4.44533109664917}}},"scale":{"nam":"vec3","dat":{"x":{"nam":"float","dat":1.0},"y":{"nam":"float","dat":1.0},"z":{"nam":"float","dat":1.0}}},"zLayer":{"nam":"float","dat":0.0},"rotation":{"nam":"float","dat":0.0},"parent":{"nam":"GameObject","dat":{"id":{"nam":"int","dat":0}}}}},{"nam":"ScriptComponent","dat":[{"nam":"LuaScript","dat":{"thisObject":{"nam":"GameObject","dat":{"id":{"nam":"int","dat":1626}}},"resourceID":{"nam":"unsigned long long","dat":1207201601},"vars":{"CoinValue":{"nam":"double","dat":1.0},"TotalScore":{"nam":"double","dat":0.0},"Player2_Health":{"nam":"double","dat":10.0},"GemsCollected":{"nam":"double","dat":0.0},"Player1_Health":{"nam":"double","dat":10.0},"TotalLives":{"nam":"double","dat":5.0}}}}]}]},{"objID":1627,"componentArray":[{"nam":"ObjectInfo","dat":{"savesWithLevel":{"nam":"bool","dat":true},"id":{"nam":"int","dat":1627},"tags":{"nam":"TagMap","dat":{}},"name":{"nam":"std::string","dat":"Background"},"destroyed":{"nam":"bool","dat":false},"active":{"nam":"bool","dat":true}}},{"nam":"TransformComponent","dat":{"position":{"nam":"vec2","dat":{"x":{"nam":"float","dat":0.0},"y":{"nam":"float","dat":0.0}}},"scale":{"nam":"vec3","dat":{"x":{"nam":"float","dat":1.0},"y":{"nam":"float","dat":1.0},"z":{"nam":"float","dat":1.0}}},"zLayer":{"nam":"float","dat":-99.0},"rotation":{"nam":"float","dat":0.0},"parent":{"nam":"GameObject","dat":{"id":{"nam":"int","dat":0}}}}},{"nam":"ScriptComponent","dat":[{"nam":"LuaScript","dat":{"thisObject":{"nam":"GameObject","dat":{"id":{"nam":"int","dat":1627}}},"resourceID":{"nam":"unsigned long long","dat":175443277},"vars":{"started":{"nam":"bool","dat":false},"SONG_NAME":{"nam":"std::string","dat":"level_1.mp3"},"VOLUME":{"nam":"double","dat":0.4}}}}]},{"nam":"BackgroundComponent","dat":{"resourceID":{"nam":"unsigned long long","dat":871361154},"subTextureSize":{"nam":"vec2","dat":{"x":{"nam":"float","dat":0.5},"y":{"nam":"float","dat":1.0}}},"backgroundType":{"nam":"int","dat":2},"parallaxBounds":{"nam":"glm::vec4","dat":{"x":{"nam":"float","dat":8.0},"y":{"nam":"float","dat":-25.0},"z":{"nam":"float","dat":100.0},"w":{"nam":"float","dat":25.0}}},"subTexturePosition":{"nam":"vec2","dat":{"x":{"nam":"float","dat":0.0},"y":{"nam":"float","dat":0.5}}},"textureXRange":{"nam":"vec2","dat":{"x":{"nam":"float","dat":0.0},"y":{"nam":"float","dat":1.0}}},"textureYRange":{"nam":"vec2","dat":{"x":{"nam":"float","dat":1.0},"y":{"nam":"float","dat":0.0}}}}}]},{"objID":1628,"componentArray":[{"nam":"ObjectInfo","dat":{"savesWithLevel":{"nam":"bool","dat":true},"id":{"nam":"int","dat":1628},"tags":{"nam":"TagMap","dat":{"Coin":216141169}},"name":{"nam":"std::string","dat":"Coin"},"destroyed":{"nam":"bool","dat":false},"active":{"nam":"bool","dat":true}}},{"nam":"TransformComponent","dat":{"position":{"nam":"vec2","dat":{"x":{"nam":"float","dat":-13.967540740966797},"y":{"nam":"float","dat":-12.279402732849121}}},"scale":{"nam":"vec3","dat":{"x":{"nam":"float","dat":0.5},"y":{"nam":"float","dat":0.5},"z":{"nam":"float","dat":1.0}}},"zLayer":{"nam":"float","dat":0.0},"rotation":{"nam":"float","dat":0.0},"parent":{"nam":"GameObject","dat":{"id":{"nam":"int","dat":0}}}}},{"nam":"StaticCollider2DComponent","dat":{"colliderData":{"nam":"Collider2D","dat":{"selfElasticity":{"nam":"float","dat":0.0},"colliderShape":{"nam":"int","dat":3},"offset":{"nam":"vec3","dat":{"x":{"nam":"float","dat":0.0},"y":{"nam":"float","dat":0.0},"z":{"nam":"float","dat":0.0}}},"collisionLayer":{"nam":"CollisionLayer","dat":{"layer":{"nam":"int","dat":2}}},"dimensions":{"nam":"vec3","dat":{"x":{"nam":"float","dat":0.5},"y":{"nam":"float","dat":0.5},"z":{"nam":"float","dat":1.0}}},"rotationOffset":{"nam":"float","dat":0.0},"layersCollidedWith":{"nam":"int","dat":0},"collisionType":{"nam":"collisionType","dat":1},"appliedElasticity":{"nam":"float","dat":0.0}}}}},{"nam":"SpriteComponent","dat":{"id":{"nam":"unsigned long long","dat":2704835172},"textureHandler":{"nam":"TextureHandler","dat":{"timer":{"nam":"float","dat":0.0},"isTiling":{"nam":"bool","dat":false},"tileAmount":{"nam":"vec2","dat":{"x":{"nam":"float","dat":1.0},"y":{"nam":"float","dat":1.0}}},"isAnimated":{"nam":"bool","dat":false},"currentFrame":{"nam":"int","dat":0},"id":{"nam":"unsigned long long","dat":2704835172},"fps":{"nam":"float","dat":0.0}}},"color":{"nam":"glm::vec4","dat":{"x":{"nam":"float","dat":1.0},"y":{"nam":"float","dat":1.0},"z":{"nam":"float","dat":1.0},"w":{"nam":"float","dat":1.0}}}}},{"nam":"ScriptComponent","dat":[{"nam":"LuaScript","dat":{"thisObject":{"nam":"GameObject","dat":{"id":{"nam":"int","dat":1628}}},"resourceID":{"nam":"unsigned long long","dat":3549609046},"vars":{}}}]}]},{"objID":1629,"componentArray":[{"nam":"ObjectInfo","dat":{"savesWithLevel":{"nam":"bool","dat":true},"id":{"nam":"int","dat":1629},"tags":{"nam":"TagMap","dat":{}},"name":{"nam":"std::string","dat":"Interactive1"},"destroyed":{"nam":"bool","dat":false},"active":{"nam":"bool","dat":true}}},{"nam":"TransformComponent","dat":{"position":{"nam":"vec2","dat":{"x":{"nam":"float","dat":13.718374252319336},"y":{"nam":"float","dat":-9.257853507995606}}},"scale":{"nam":"vec3","dat":{"x":{"nam":"float","dat":1.0},"y":{"nam":"float","dat":1.2000000476837159},"z":{"nam":"float","dat":1.0}}},"zLayer":{"nam":"float","dat":0.0},"rotation":{"nam":"float","dat":0.0},"parent":{"nam":"GameObject","dat":{"id":{"nam":"int","dat":0}}}}},{"nam":"StaticCollider2DComponent","dat":{"colliderData":{"nam":"Collider2D","dat":{"selfElasticity":{"nam":"float","dat":0.0},"colliderShape":{"nam":"int","dat":3},"offset":{"nam":"vec3","dat":{"x":{"nam":"float","dat":0.0},"y":{"nam":"float","dat":0.0},"z":{"nam":"float","dat":0.0}}},"collisionLayer":{"nam":"CollisionLayer","dat":{"layer":{"nam":"int","dat":2}}},"dimensions":{"nam":"vec3","dat":{"x":{"nam":"float","dat":1.0},"y":{"nam":"float","dat":1.2000000476837159},"z":{"nam":"float","dat":1.0}}},"rotationOffset":{"nam":"float","dat":0.0},"layersCollidedWith":{"nam":"int","dat":0},"collisionType":{"nam":"collisionType","dat":1},"appliedElasticity":{"nam":"float","dat":0.0}}}}},{"nam":"SpriteComponent","dat":{"id":{"nam":"unsigned long long","dat":928961439},"textureHandler":{"nam":"TextureHandler","dat":{"timer":{"nam":"float","dat":0.0},"isTiling":{"nam":"bool","dat":false},"tileAmount":{"nam":"vec2","dat":{"x":{"nam":"float","dat":1.0},"y":{"nam":"float","dat":1.0}}},"isAnimated":{"nam":"bool","dat":false},"currentFrame":{"nam":"int","dat":0},"id":{"nam":"unsigned long long","dat":928961439},"fps":{"nam":"float","dat":0.0}}},"color":{"nam":"glm::vec4","dat":{"x":{"nam":"float","dat":1.0},"y":{"nam":"float","dat":1.0},"z":{"nam":"float","dat":1.0},"w":{"nam":"float","dat":1.0}}}}}]},{"objID":1630,"componentArray":[{"nam":"ObjectInfo","dat":{"savesWithLevel":{"nam":"bool","dat":true},"id":{"nam":"int","dat":1630},"tags":{"nam":"TagMap","dat":{"Player":3563643746}},"name":{"nam":"std::string","dat":"StoneGnome"},"destroyed":{"nam":"bool","dat":false},"active":{"nam":"bool","dat":true}}},{"nam":"TransformComponent","dat":{"position":{"nam":"vec2","dat":{"x":{"nam":"float","dat":-14.46113109588623},"y":{"nam":"float","dat":-86066768.0}}},"scale":{"nam":"vec3","dat":{"x":{"nam":"float","dat":1.0},"y":{"nam":"float","dat":1.0},"z":{"nam":"float","dat":1.0}}},"zLayer":{"nam":"float","dat":0.0},"rotation":{"nam":"float","dat":13.472809791564942},"parent":{"nam":"GameObject","dat":{"id":{"nam":"int","dat":0}}}}},{"nam":"RigidBodyComponent","dat":{"gravity":{"nam":"vec3","dat":{"x":{"nam":"float","dat":0.0},"y":{"nam":"float","dat":-9.0},"z":{"nam":"float","dat":0.0}}},"acceleration":{"nam":"vec3","dat":{"x":{"nam":"float","dat":0.0},"y":{"nam":"float","dat":0.0},"z":{"nam":"float","dat":0.0}}},"velocity":{"nam":"vec3","dat":{"x":{"nam":"float","dat":0.0},"y":{"nam":"float","dat":-39369.66796875},"z":{"nam":"float","dat":0.0}}},"mass":{"nam":"float","dat":0.0}}},{"nam":"SpriteComponent","dat":{"id":{"nam":"unsigned long long","dat":3032232252},"textureHandler":{"nam":"TextureHandler","dat":{"timer":{"nam":"float","dat":2531.73779296875},"isTiling":{"nam":"bool","dat":false},"tileAmount":{"nam":"vec2","dat":{"x":{"nam":"float","dat":1.0},"y":{"nam":"float","dat":1.0}}},"isAnimated":{"nam":"bool","dat":true},"currentFrame":{"nam":"int","dat":0},"id":{"nam":"unsigned long long","dat":3032232252},"fps":{"nam":"float","dat":0.0}}},"color":{"nam":"glm::vec4","dat":{"x":{"nam":"float","dat":0.04052014276385307},"y":{"nam":"float","dat":0.039381708949804309},"z":{"nam":"float","dat":0.041379332542419437},"w":{"nam":"float","dat":1.0}}}}}]},{"objID":1631,"componentArray":[{"nam":"ObjectInfo","dat":{"savesWithLevel":{"nam":"bool","dat":true},"id":{"nam":"int","dat":1631},"tags":{"nam":"TagMap","dat":{}},"name":{"nam":"std::string","dat":"Coin"},"destroyed":{"nam":"bool","dat":false},"active":{"nam":"bool","dat":true}}},{"nam":"TransformComponent","dat":{"position":{"nam":"vec2","dat":{"x":{"nam":"float","dat":5098.2275390625},"y":{"nam":"float","dat":-20823242.0}}},"scale":{"nam":"vec3","dat":{"x":{"nam":"float","dat":-1.25},"y":{"nam":"float","dat":2.0},"z":{"nam":"float","dat":1.0}}},"zLayer":{"nam":"float","dat":0.0},"rotation":{"nam":"float","dat":0.0},"parent":{"nam":"GameObject","dat":{"id":{"nam":"int","dat":0}}}}},{"nam":"RigidBodyComponent","dat":{"gravity":{"nam":"vec3","dat":{"x":{"nam":"float","dat":0.0},"y":{"nam":"float","dat":-9.0},"z":{"nam":"float","dat":0.0}}},"acceleration":{"nam":"vec3","dat":{"x":{"nam":"float","dat":0.0},"y":{"nam":"float","dat":0.0},"z":{"nam":"float","dat":0.0}}},"velocity":{"nam":"vec3","dat":{"x":{"nam":"float","dat":-2.0},"y":{"nam":"float","dat":-13035.2373046875},"z":{"nam":"float","dat":0.0}}},"mass":{"nam":"float","dat":0.0}}},{"nam":"DynamicCollider2DComponent","dat":{"colliderData":{"nam":"Collider2D","dat":{"selfElasticity":{"nam":"float","dat":0.0},"colliderShape":{"nam":"int","dat":2},"offset":{"nam":"vec3","dat":{"x":{"nam":"float","dat":0.0},"y":{"nam":"float","dat":0.0},"z":{"nam":"float","dat":0.0}}},"collisionLayer":{"nam":"CollisionLayer","dat":{"layer":{"nam":"int","dat":16}}},"dimensions":{"nam":"vec3","dat":{"x":{"nam":"float","dat":1.25},"y":{"nam":"float","dat":2.0},"z":{"nam":"float","dat":1.0}}},"rotationOffset":{"nam":"float","dat":0.0},"layersCollidedWith":{"nam":"int","dat":0},"collisionType":{"nam":"collisionType","dat":0},"appliedElasticity":{"nam":"float","dat":0.0}}}}},{"nam":"SpriteComponent","dat":{"id":{"nam":"unsigned long long","dat":651912714},"textureHandler":{"nam":"TextureHandler","dat":{"timer":{"nam":"float","dat":0.0},"isTiling":{"nam":"bool","dat":false},"tileAmount":{"nam":"vec2","dat":{"x":{"nam":"float","dat":1.0},"y":{"nam":"float","dat":1.0}}},"isAnimated":{"nam":"bool","dat":false},"currentFrame":{"nam":"int","dat":0},"id":{"nam":"unsigned long long","dat":651912714},"fps":{"nam":"float","dat":0.0}}},"color":{"nam":"glm::vec4","dat":{"x":{"nam":"float","dat":1.0},"y":{"nam":"float","dat":1.0},"z":{"nam":"float","dat":1.0},"w":{"nam":"float","dat":1.0}}}}},{"nam":"ScriptComponent","dat":[{"nam":"LuaScript","dat":{"thisObject":{"nam":"GameObject","dat":{"id":{"nam":"int","dat":1631}}},"resourceID":{"nam":"unsigned long long","dat":1476025226},"vars":{"GROUND_LAYER":{"nam":"double","dat":8.0},"DAMAGE_FLASH_TIME":{"nam":"double","dat":0.1},"damageFlashTimer":{"nam":"double","dat":-681.8032272383571},"speed":{"nam":"double","dat":2.0},"ALLY_PROJECTILE_LAYER":{"nam":"double","dat":32.0},"scared":{"nam":"bool","dat":false},"health":{"nam":"double","dat":10.0},"scaredSpeed":{"nam":"double","dat":3.0},"direction":{"nam":"double","dat":-1.0}}}}]}]},{"objID":1632,"componentArray":[{"nam":"ObjectInfo","dat":{"savesWithLevel":{"nam":"bool","dat":true},"id":{"nam":"int","dat":1632},"tags":{"nam":"TagMap","dat":{"Player":3563643746}},"name":{"nam":"std::string","dat":"StoneGnome"},"destroyed":{"nam":"bool","dat":false},"active":{"nam":"bool","dat":true}}},{"nam":"TransformComponent","dat":{"position":{"nam":"vec2","dat":{"x":{"nam":"float","dat":-11.207148551940918},"y":{"nam":"float","dat":-86066768.0}}},"scale":{"nam":"vec3","dat":{"x":{"nam":"float","dat":1.0},"y":{"nam":"float","dat":1.0},"z":{"nam":"float","dat":1.0}}},"zLayer":{"nam":"float","dat":0.0},"rotation":{"nam":"float","dat":-2.900869369506836},"parent":{"nam":"GameObject","dat":{"id":{"nam":"int","dat":0}}}}},{"nam":"RigidBodyComponent","dat":{"gravity":{"nam":"vec3","dat":{"x":{"nam":"float","dat":0.0},"y":{"nam":"float","dat":-9.0},"z":{"nam":"float","dat":0.0}}},"acceleration":{"nam":"vec3","dat":{"x":{"nam":"float","dat":0.0},"y":{"nam":"float","dat":0.0},"z":{"nam":"float","dat":0.0}}},"velocity":{"nam":"vec3","dat":{"x":{"nam":"float","dat":0.0},"y":{"nam":"float","dat":-39369.66796875},"z":{"nam":"float","dat":0.0}}},"mass":{"nam":"float","dat":0.0}}},{"nam":"SpriteComponent","dat":{"id":{"nam":"unsigned long long","dat":3032232252},"textureHandler":{"nam":"TextureHandler","dat":{"timer":{"nam":"float","dat":2531.73779296875},"isTiling":{"nam":"bool","dat":false},"tileAmount":{"nam":"vec2","dat":{"x":{"nam":"float","dat":1.0},"y":{"nam":"float","dat":1.0}}},"isAnimated":{"nam":"bool","dat":true},"currentFrame":{"nam":"int","dat":0},"id":{"nam":"unsigned long long","dat":3032232252},"fps":{"nam":"float","dat":0.0}}},"color":{"nam":"glm::vec4","dat":{"x":{"nam":"float","dat":0.04052014276385307},"y":{"nam":"float","dat":0.039381708949804309},"z":{"nam":"float","dat":0.041379332542419437},"w":{"nam":"float","dat":1.0}}}}}]},{"objID":1633,"componentArray":[{"nam":"ObjectInfo","dat":{"savesWithLevel":{"nam":"bool","dat":true},"id":{"nam":"int","dat":1633},"tags":{"nam":"TagMap","dat":{}},"name":{"nam":"std::string","dat":"DangerShroom"},"destroyed":{"nam":"bool","dat":false},"active":{"nam":"bool","dat":true}}},{"nam":"TransformComponent","dat":{"position":{"nam":"vec2","dat":{"x":{"nam":"float","dat":25.700481414794923},"y":{"nam":"float","dat":-13.168744087219239}}},"scale":{"nam":"vec3","dat":{"x":{"nam":"float","dat":1.0},"y":{"nam":"float","dat":1.0},"z":{"nam":"float","dat":1.0}}},"zLayer":{"nam":"float","dat":0.0},"rotation":{"nam":"float","dat":0.0},"parent":{"nam":"GameObject","dat":{"id":{"nam":"int","dat":0}}}}},{"nam":"SpriteComponent","dat":{"id":{"nam":"unsigned long long","dat":2345060871},"textureHandler":{"nam":"TextureHandler","dat":{"timer":{"nam":"float","dat":0.0},"isTiling":{"nam":"bool","dat":false},"tileAmount":{"nam":"vec2","dat":{"x":{"nam":"float","dat":1.0},"y":{"nam":"float","dat":1.0}}},"isAnimated":{"nam":"bool","dat":false},"currentFrame":{"nam":"int","dat":0},"id":{"nam":"unsigned long long","dat":2345060871},"fps":{"nam":"float","dat":0.0}}},"color":{"nam":"glm::vec4","dat":{"x":{"nam":"float","dat":1.0},"y":{"nam":"float","dat":1.0},"z":{"nam":"float","dat":1.0},"w":{"nam":"float","dat":1.0}}}}},{"nam":"ScriptComponent","dat":[{"nam":"LuaScript","dat":{"thisObject":{"nam":"GameObject","dat":{"id":{"nam":"int","dat":1633}}},"resourceID":{"nam":"unsigned long long","dat":4025773346},"vars":{"XVelocity":{"nam":"double","dat":0.0},"SPORE":{"nam":"std::string","dat":"assets/prefabs/dangerShroom_Spore.json"},"YVelocity":{"nam":"double","dat":0.0},"SpawnTimer":{"nam":"double","dat":0.3976318359375002},"SpawnDir":{"nam":"double","dat":1.0},"SpawnTimerMax":{"nam":"double","dat":3.2}}}}]}]},{"objID":1634,"componentArray":[{"nam":"ObjectInfo","dat":{"savesWithLevel":{"nam":"bool","dat":true},"id":{"nam":"int","dat":1634},"tags":{"nam":"TagMap","dat":{}},"name":{"nam":"std::string","dat":"Coin"},"destroyed":{"nam":"bool","dat":false},"active":{"nam":"bool","dat":false}}},{"nam":"TransformComponent","dat":{"position":{"nam":"vec2","dat":{"x":{"nam":"float","dat":-6.098295211791992},"y":{"nam":"float","dat":-7.091244220733643}}},"scale":{"nam":"vec3","dat":{"x":{"nam":"float","dat":0.5},"y":{"nam":"float","dat":0.5},"z":{"nam":"float","dat":1.0}}},"zLayer":{"nam":"float","dat":0.0},"rotation":{"nam":"float","dat":0.0},"parent":{"nam":"GameObject","dat":{"id":{"nam":"int","dat":0}}}}},{"nam":"StaticCollider2DComponent","dat":{"colliderData":{"nam":"Collider2D","dat":{"selfElasticity":{"nam":"float","dat":0.0},"colliderShape":{"nam":"int","dat":3},"offset":{"nam":"vec3","dat":{"x":{"nam":"float","dat":0.0},"y":{"nam":"float","dat":0.0},"z":{"nam":"float","dat":0.0}}},"collisionLayer":{"nam":"CollisionLayer","dat":{"layer":{"nam":"int","dat":2}}},"dimensions":{"nam":"vec3","dat":{"x":{"nam":"float","dat":0.5},"y":{"nam":"float","dat":0.5},"z":{"nam":"float","dat":1.0}}},"rotationOffset":{"nam":"float","dat":0.0},"layersCollidedWith":{"nam":"int","dat":0},"collisionType":{"nam":"collisionType","dat":1},"appliedElasticity":{"nam":"float","dat":0.0}}}}},{"nam":"SpriteComponent","dat":{"id":{"nam":"unsigned long long","dat":2704835172},"textureHandler":{"nam":"TextureHandler","dat":{"timer":{"nam":"float","dat":0.0},"isTiling":{"nam":"bool","dat":false},"tileAmount":{"nam":"vec2","dat":{"x":{"nam":"float","dat":1.0},"y":{"nam":"float","dat":1.0}}},"isAnimated":{"nam":"bool","dat":false},"currentFrame":{"nam":"int","dat":0},"id":{"nam":"unsigned long long","dat":2704835172},"fps":{"nam":"float","dat":0.0}}},"color":{"nam":"glm::vec4","dat":{"x":{"nam":"float","dat":1.0},"y":{"nam":"float","dat":1.0},"z":{"nam":"float","dat":1.0},"w":{"nam":"float","dat":1.0}}}}},{"nam":"ScriptComponent","dat":[{"nam":"LuaScript","dat":{"thisObject":{"nam":"GameObject","dat":{"id":{"nam":"int","dat":1634}}},"resourceID":{"nam":"unsigned long long","dat":3549609046},"vars":{}}}]}]},{"objID":1635,"componentArray":[{"nam":"ObjectInfo","dat":{"savesWithLevel":{"nam":"bool","dat":true},"id":{"nam":"int","dat":1635},"tags":{"nam":"TagMap","dat":{"Ground":185762651}},"name":{"nam":"std::string","dat":"Ground"},"destroyed":{"nam":"bool","dat":false},"active":{"nam":"bool","dat":true}}},{"nam":"TransformComponent","dat":{"position":{"nam":"vec2","dat":{"x":{"nam":"float","dat":15.378299713134766},"y":{"nam":"float","dat":-12.649313926696778}}},"scale":{"nam":"vec3","dat":{"x":{"nam":"float","dat":0.5},"y":{"nam":"float","dat":3.0},"z":{"nam":"float","dat":1.0}}},"zLayer":{"nam":"float","dat":0.0},"rotation":{"nam":"float","dat":0.0},"parent":{"nam":"GameObject","dat":{"id":{"nam":"int","dat":0}}}}},{"nam":"StaticCollider2DComponent","dat":{"colliderData":{"nam":"Collider2D","dat":{"selfElasticity":{"nam":"float","dat":0.0},"colliderShape":{"nam":"int","dat":3},"offset":{"nam":"vec3","dat":{"x":{"nam":"float","dat":0.0},"y":{"nam":"float","dat":0.0},"z":{"nam":"float","dat":0.0}}},"collisionLayer":{"nam":"CollisionLayer","dat":{"layer":{"nam":"int","dat":8}}},"dimensions":{"nam":"vec3","dat":{"x":{"nam":"float","dat":0.5},"y":{"nam":"float","dat":3.0},"z":{"nam":"float","dat":1.0}}},"rotationOffset":{"nam":"float","dat":0.0},"layersCollidedWith":{"nam":"int","dat":0},"collisionType":{"nam":"collisionType","dat":0},"appliedElasticity":{"nam":"float","dat":0.0}}}}},{"nam":"SpriteComponent","dat":{"id":{"nam":"unsigned long long","dat":709983426},"textureHandler":{"nam":"TextureHandler","dat":{"timer":{"nam":"float","dat":0.0},"isTiling":{"nam":"bool","dat":true},"tileAmount":{"nam":"vec2","dat":{"x":{"nam":"float","dat":2.0},"y":{"nam":"float","dat":2.0}}},"isAnimated":{"nam":"bool","dat":false},"currentFrame":{"nam":"int","dat":0},"id":{"nam":"unsigned long long","dat":709983426},"fps":{"nam":"float","dat":0.0}}},"color":{"nam":"glm::vec4","dat":{"x":{"nam":"float","dat":1.0},"y":{"nam":"float","dat":1.0},"z":{"nam":"float","dat":1.0},"w":{"nam":"float","dat":1.0}}}}}]},{"objID":1636,"componentArray":[{"nam":"ObjectInfo","dat":{"savesWithLevel":{"nam":"bool","dat":true},"id":{"nam":"int","dat":1636},"tags":{"nam":"TagMap","dat":{}},"name":{"nam":"std::string","dat":"Coin"},"destroyed":{"nam":"bool","dat":false},"active":{"nam":"bool","dat":true}}},{"nam":"TransformComponent","dat":{"position":{"nam":"vec2","dat":{"x":{"nam":"float","dat":32.970001220703128},"y":{"nam":"float","dat":48.0}}},"scale":{"nam":"vec3","dat":{"x":{"nam":"float","dat":1.0},"y":{"nam":"float","dat":0.5},"z":{"nam":"float","dat":1.0}}},"zLayer":{"nam":"float","dat":0.0},"rotation":{"nam":"float","dat":0.0},"parent":{"nam":"GameObject","dat":{"id":{"nam":"int","dat":0}}}}},{"nam":"StaticCollider2DComponent","dat":{"colliderData":{"nam":"Collider2D","dat":{"selfElasticity":{"nam":"float","dat":0.0},"colliderShape":{"nam":"int","dat":3},"offset":{"nam":"vec3","dat":{"x":{"nam":"float","dat":0.0},"y":{"nam":"float","dat":0.0},"z":{"nam":"float","dat":0.0}}},"collisionLayer":{"nam":"CollisionLayer","dat":{"layer":{"nam":"int","dat":2}}},"dimensions":{"nam":"vec3","dat":{"x":{"nam":"float","dat":1.0},"y":{"nam":"float","dat":0.5},"z":{"nam":"float","dat":1.0}}},"rotationOffset":{"nam":"float","dat":0.0},"layersCollidedWith":{"nam":"int","dat":0},"collisionType":{"nam":"collisionType","dat":0},"appliedElasticity":{"nam":"float","dat":0.0}}}}},{"nam":"SpriteComponent","dat":{"id":{"nam":"unsigned long long","dat":2704835172},"textureHandler":{"nam":"TextureHandler","dat":{"timer":{"nam":"float","dat":0.0},"isTiling":{"nam":"bool","dat":false},"tileAmount":{"nam":"vec2","dat":{"x":{"nam":"float","dat":1.0},"y":{"nam":"float","dat":1.0}}},"isAnimated":{"nam":"bool","dat":false},"currentFrame":{"nam":"int","dat":0},"id":{"nam":"unsigned long long","dat":2704835172},"fps":{"nam":"float","dat":0.0}}},"color":{"nam":"glm::vec4","dat":{"x":{"nam":"float","dat":1.0},"y":{"nam":"float","dat":1.0},"z":{"nam":"float","dat":1.0},"w":{"nam":"float","dat":1.0}}}}}]},{"objID":1637,"componentArray":[{"nam":"ObjectInfo","dat":{"savesWithLevel":{"nam":"bool","dat":true},"id":{"nam":"int","dat":1637},"tags":{"nam":"TagMap","dat":{"Player":3563643746}},"name":{"nam":"std::string","dat":"StoneGnome"},"destroyed":{"nam":"bool","dat":false},"active":{"nam":"bool","dat":true}}},{"nam":"TransformComponent","dat":{"position":{"nam":"vec2","dat":{"x":{"nam":"float","dat":-5.8058977127075199},"y":{"nam":"float","dat":-86066768.0}}},"scale":{"nam":"vec3","dat":{"x":{"nam":"float","dat":1.0},"y":{"nam":"float","dat":1.0},"z":{"nam":"float","dat":1.0}}},"zLayer":{"nam":"float","dat":-1.0},"rotation":{"nam":"float","dat":-12.668577194213868},"parent":{"nam":"GameObject","dat":{"id":{"nam":"int","dat":0}}}}},{"nam":"RigidBodyComponent","dat":{"gravity":{"nam":"vec3","dat":{"x":{"nam":"float","dat":0.0},"y":{"nam":"float","dat":-9.0},"z":{"nam":"float","dat":0.0}}},"acceleration":{"nam":"vec3","dat":{"x":{"nam":"float","dat":0.0},"y":{"nam":"float","dat":0.0},"z":{"nam":"float","dat":0.0}}},"velocity":{"nam":"vec3","dat":{"x":{"nam":"float","dat":0.0},"y":{"nam":"float","dat":-39369.66796875},"z":{"nam":"float","dat":0.0}}},"mass":{"nam":"float","dat":0.0}}},{"nam":"SpriteComponent","dat":{"id":{"nam":"unsigned long long","dat":3032232252},"textureHandler":{"nam":"TextureHandler","dat":{"timer":{"nam":"float","dat":2531.73779296875},"isTiling":{"nam":"bool","dat":false},"tileAmount":{"nam":"vec2","dat":{"x":{"nam":"float","dat":1.0},"y":{"nam":"float","dat":1.0}}},"isAnimated":{"nam":"bool","dat":true},"currentFrame":{"nam":"int","dat":0},"id":{"nam":"unsigned long long","dat":3032232252},"fps":{"nam":"float","dat":0.0}}},"color":{"nam":"glm::vec4","dat":{"x":{"nam":"float","dat":0.04052014276385307},"y":{"nam":"float","dat":0.039381708949804309},"z":{"nam":"float","dat":0.041379332542419437},"w":{"nam":"float","dat":1.0}}}}}]},{"objID":1638,"componentArray":[{"nam":"ObjectInfo","dat":{"savesWithLevel":{"nam":"bool","dat":true},"id":{"nam":"int","dat":1638},"tags":{"nam":"TagMap","dat":{}},"name":{"nam":"std::string","dat":"Wall"},"destroyed":{"nam":"bool","dat":false},"active":{"nam":"bool","dat":true}}},{"nam":"TransformComponent","dat":{"position":{"nam":"vec2","dat":{"x":{"nam":"float","dat":-16.627120971679689},"y":{"nam":"float","dat":1.4812300205230713}}},"scale":{"nam":"vec3","dat":{"x":{"nam":"float","dat":1.0},"y":{"nam":"float","dat":1.0},"z":{"nam":"float","dat":1.0}}},"zLayer":{"nam":"float","dat":0.0},"rotation":{"nam":"float","dat":0.0},"parent":{"nam":"GameObject","dat":{"id":{"nam":"int","dat":0}}}}},{"nam":"StaticCollider2DComponent","dat":{"colliderData":{"nam":"Collider2D","dat":{"selfElasticity":{"nam":"float","dat":0.0},"colliderShape":{"nam":"int","dat":3},"offset":{"nam":"vec3","dat":{"x":{"nam":"float","dat":0.0},"y":{"nam":"float","dat":0.0},"z":{"nam":"float","dat":0.0}}},"collisionLayer":{"nam":"CollisionLayer","dat":{"layer":{"nam":"int","dat":2}}},"dimensions":{"nam":"vec3","dat":{"x":{"nam":"float","dat":1.0},"y":{"nam":"float","dat":7.28000020980835},"z":{"nam":"float","dat":0.0}}},"rotationOffset":{"nam":"float","dat":0.0},"layersCollidedWith":{"nam":"int","dat":0},"collisionType":{"nam":"collisionType","dat":0},"appliedElasticity":{"nam":"float","dat":0.0}}}}}]},{"objID":1639,"componentArray":[{"nam":"ObjectInfo","dat":{"savesWithLevel":{"nam":"bool","dat":true},"id":{"nam":"int","dat":1639},"tags":{"nam":"TagMap","dat":{}},"name":{"nam":"std::string","dat":"Coin"},"destroyed":{"nam":"bool","dat":false},"active":{"nam":"bool","dat":true}}},{"nam":"TransformComponent","dat":{"position":{"nam":"vec2","dat":{"x":{"nam":"float","dat":1677.709228515625},"y":{"nam":"float","dat":-9441126.0}}},"scale":{"nam":"vec3","dat":{"x":{"nam":"float","dat":-1.25},"y":{"nam":"float","dat":2.0},"z":{"nam":"float","dat":1.0}}},"zLayer":{"nam":"float","dat":0.0},"rotation":{"nam":"float","dat":0.0},"parent":{"nam":"GameObject","dat":{"id":{"nam":"int","dat":0}}}}},{"nam":"RigidBodyComponent","dat":{"gravity":{"nam":"vec3","dat":{"x":{"nam":"float","dat":0.0},"y":{"nam":"float","dat":-9.0},"z":{"nam":"float","dat":0.0}}},"acceleration":{"nam":"vec3","dat":{"x":{"nam":"float","dat":0.0},"y":{"nam":"float","dat":0.0},"z":{"nam":"float","dat":0.0}}},"velocity":{"nam":"vec3","dat":{"x":{"nam":"float","dat":-2.0},"y":{"nam":"float","dat":-13035.2373046875},"z":{"nam":"float","dat":0.0}}},"mass":{"nam":"float","dat":0.0}}},{"nam":"DynamicCollider2DComponent","dat":{"colliderData":{"nam":"Collider2D","dat":{"selfElasticity":{"nam":"float","dat":0.0},"colliderShape":{"nam":"int","dat":2},"offset":{"nam":"vec3","dat":{"x":{"nam":"float","dat":0.0},"y":{"nam":"float","dat":0.0},"z":{"nam":"float","dat":0.0}}},"collisionLayer":{"nam":"CollisionLayer","dat":{"layer":{"nam":"int","dat":16}}},"dimensions":{"nam":"vec3","dat":{"x":{"nam":"float","dat":1.25},"y":{"nam":"float","dat":2.0},"z":{"nam":"float","dat":1.0}}},"rotationOffset":{"nam":"float","dat":0.0},"layersCollidedWith":{"nam":"int","dat":0},"collisionType":{"nam":"collisionType","dat":0},"appliedElasticity":{"nam":"float","dat":0.0}}}}},{"nam":"SpriteComponent","dat":{"id":{"nam":"unsigned long long","dat":651912714},"textureHandler":{"nam":"TextureHandler","dat":{"timer":{"nam":"float","dat":0.0},"isTiling":{"nam":"bool","dat":false},"tileAmount":{"nam":"vec2","dat":{"x":{"nam":"float","dat":1.0},"y":{"nam":"float","dat":1.0}}},"isAnimated":{"nam":"bool","dat":false},"currentFrame":{"nam":"int","dat":0},"id":{"nam":"unsigned long long","dat":651912714},"fps":{"nam":"float","dat":0.0}}},"color":{"nam":"glm::vec4","dat":{"x":{"nam":"float","dat":1.0},"y":{"nam":"float","dat":1.0},"z":{"nam":"float","dat":1.0},"w":{"nam":"float","dat":1.0}}}}},{"nam":"ScriptComponent","dat":[{"nam":"LuaScript","dat":{"thisObject":{"nam":"GameObject","dat":{"id":{"nam":"int","dat":1639}}},"resourceID":{"nam":"unsigned long long","dat":1476025226},"vars":{"GROUND_LAYER":{"nam":"double","dat":8.0},"DAMAGE_FLASH_TIME":{"nam":"double","dat":0.1},"damageFlashTimer":{"nam":"double","dat":-681.8032272383571},"speed":{"nam":"double","dat":2.0},"ALLY_PROJECTILE_LAYER":{"nam":"double","dat":32.0},"scared":{"nam":"bool","dat":false},"health":{"nam":"double","dat":10.0},"scaredSpeed":{"nam":"double","dat":3.0},"direction":{"nam":"double","dat":-1.0}}}}]}]},{"objID":1640,"componentArray":[{"nam":"ObjectInfo","dat":{"savesWithLevel":{"nam":"bool","dat":true},"id":{"nam":"int","dat":1640},"tags":{"nam":"TagMap","dat":{}},"name":{"nam":"std::string","dat":"Tree3"},"destroyed":{"nam":"bool","dat":false},"active":{"nam":"bool","dat":true}}},{"nam":"TransformComponent","dat":{"position":{"nam":"vec2","dat":{"x":{"nam":"float","dat":1.3068923950195313},"y":{"nam":"float","dat":-12.21701431274414}}},"scale":{"nam":"vec3","dat":{"x":{"nam":"float","dat":9.546624183654786},"y":{"nam":"float","dat":11.78600025177002},"z":{"nam":"float","dat":1.0}}},"zLayer":{"nam":"float","dat":-2.0},"rotation":{"nam":"float","dat":0.0},"parent":{"nam":"GameObject","dat":{"id":{"nam":"int","dat":0}}}}},{"nam":"SpriteComponent","dat":{"id":{"nam":"unsigned long long","dat":4078474189},"textureHandler":{"nam":"TextureHandler","dat":{"timer":{"nam":"float","dat":0.0},"isTiling":{"nam":"bool","dat":false},"tileAmount":{"nam":"vec2","dat":{"x":{"nam":"float","dat":1.0},"y":{"nam":"float","dat":1.0}}},"isAnimated":{"nam":"bool","dat":false},"currentFrame":{"nam":"int","dat":0},"id":{"nam":"unsigned long long","dat":4078474189},"fps":{"nam":"float","dat":0.0}}},"color":{"nam":"glm::vec4","dat":{"x":{"nam":"float","dat":1.0},"y":{"nam":"float","dat":1.0},"z":{"nam":"float","dat":1.0},"w":{"nam":"float","dat":1.0}}}}}]},{"objID":1641,"componentArray":[{"nam":"ObjectInfo","dat":{"savesWithLevel":{"nam":"bool","dat":true},"id":{"nam":"int","dat":1641},"tags":{"nam":"TagMap","dat":{"Ground":185762651}},"name":{"nam":"std::string","dat":"Rock_Filler"},"destroyed":{"nam":"bool","dat":false},"active":{"nam":"bool","dat":true}}},{"nam":"TransformComponent","dat":{"position":{"nam":"vec2","dat":{"x":{"nam":"float","dat":-9.64407730102539},"y":{"nam":"float","dat":-6.045809745788574}}},"scale":{"nam":"vec3","dat":{"x":{"nam":"float","dat":0.5},"y":{"nam":"float","dat":1.2319798469543458},"z":{"nam":"float","dat":1.0}}},"zLayer":{"nam":"float","dat":0.0},"rotation":{"nam":"float","dat":0.0},"parent":{"nam":"GameObject","dat":{"id":{"nam":"int","dat":0}}}}},{"nam":"SpriteComponent","dat":{"id":{"nam":"unsigned long long","dat":709983426},"textureHandler":{"nam":"TextureHandler","dat":{"timer":{"nam":"float","dat":0.0},"isTiling":{"nam":"bool","dat":true},"tileAmount":{"nam":"vec2","dat":{"x":{"nam":"float","dat":2.0},"y":{"nam":"float","dat":2.0}}},"isAnimated":{"nam":"bool","dat":false},"currentFrame":{"nam":"int","dat":0},"id":{"nam":"unsigned long long","dat":709983426},"fps":{"nam":"float","dat":0.0}}},"color":{"nam":"glm::vec4","dat":{"x":{"nam":"float","dat":0.6470588445663452},"y":{"nam":"float","dat":0.6470588445663452},"z":{"nam":"float","dat":0.6470588445663452},"w":{"nam":"float","dat":1.0}}}}}]},{"objID":1642,"componentArray":[{"nam":"ObjectInfo","dat":{"savesWithLevel":{"nam":"bool","dat":true},"id":{"nam":"int","dat":1642},"tags":{"nam":"TagMap","dat":{}},"name":{"nam":"std::string","dat":"Coin"},"destroyed":{"nam":"bool","dat":false},"active":{"nam":"bool","dat":true}}},{"nam":"TransformComponent","dat":{"position":{"nam":"vec2","dat":{"x":{"nam":"float","dat":113.08953857421875},"y":{"nam":"float","dat":-9441105.0}}},"scale":{"nam":"vec3","dat":{"x":{"nam":"float","dat":-1.25},"y":{"nam":"float","dat":2.0},"z":{"nam":"float","dat":1.0}}},"zLayer":{"nam":"float","dat":0.0},"rotation":{"nam":"float","dat":0.0},"parent":{"nam":"GameObject","dat":{"id":{"nam":"int","dat":0}}}}},{"nam":"RigidBodyComponent","dat":{"gravity":{"nam":"vec3","dat":{"x":{"nam":"float","dat":0.0},"y":{"nam":"float","dat":-9.0},"z":{"nam":"float","dat":0.0}}},"acceleration":{"nam":"vec3","dat":{"x":{"nam":"float","dat":0.0},"y":{"nam":"float","dat":0.0},"z":{"nam":"float","dat":0.0}}},"velocity":{"nam":"vec3","dat":{"x":{"nam":"float","dat":0.0},"y":{"nam":"float","dat":-13035.2373046875},"z":{"nam":"float","dat":0.0}}},"mass":{"nam":"float","dat":0.0}}},{"nam":"DynamicCollider2DComponent","dat":{"colliderData":{"nam":"Collider2D","dat":{"selfElasticity":{"nam":"float","dat":0.0},"colliderShape":{"nam":"int","dat":2},"offset":{"nam":"vec3","dat":{"x":{"nam":"float","dat":0.0},"y":{"nam":"float","dat":0.0},"z":{"nam":"float","dat":0.0}}},"collisionLayer":{"nam":"CollisionLayer","dat":{"layer":{"nam":"int","dat":16}}},"dimensions":{"nam":"vec3","dat":{"x":{"nam":"float","dat":1.25},"y":{"nam":"float","dat":2.0},"z":{"nam":"float","dat":1.0}}},"rotationOffset":{"nam":"float","dat":0.0},"layersCollidedWith":{"nam":"int","dat":0},"collisionType":{"nam":"collisionType","dat":0},"appliedElasticity":{"nam":"float","dat":0.0}}}}},{"nam":"SpriteComponent","dat":{"id":{"nam":"unsigned long long","dat":651912714},"textureHandler":{"nam":"TextureHandler","dat":{"timer":{"nam":"float","dat":0.0},"isTiling":{"nam":"bool","dat":false},"tileAmount":{"nam":"vec2","dat":{"x":{"nam":"float","dat":1.0},"y":{"nam":"float","dat":1.0}}},"isAnimated":{"nam":"bool","dat":false},"currentFrame":{"nam":"int","dat":0},"id":{"nam":"unsigned long long","dat":651912714},"fps":{"nam":"float","dat":0.0}}},"color":{"nam":"glm::vec4","dat":{"x":{"nam":"float","dat":1.0},"y":{"nam":"float","dat":1.0},"z":{"nam":"float","dat":1.0},"w":{"nam":"float","dat":1.0}}}}},{"nam":"ScriptComponent","dat":[]}]},{"objID":1643,"componentArray":[{"nam":"ObjectInfo","dat":{"savesWithLevel":{"nam":"bool","dat":true},"id":{"nam":"int","dat":1643},"tags":{"nam":"TagMap","dat":{}},"name":{"nam":"std::string","dat":"Brett"},"destroyed":{"nam":"bool","dat":false},"active":{"nam":"bool","dat":false}}},{"nam":"TransformComponent","dat":{"position":{"nam":"vec2","dat":{"x":{"nam":"float","dat":418.74859619140627},"y":{"nam":"float","dat":93.52715301513672}}},"scale":{"nam":"vec3","dat":{"x":{"nam":"float","dat":1.0},"y":{"nam":"float","dat":1.0},"z":{"nam":"float","dat":1.0}}},"zLayer":{"nam":"float","dat":-1.0},"rotation":{"nam":"float","dat":70.77000427246094},"parent":{"nam":"GameObject","dat":{"id":{"nam":"int","dat":0}}}}}]},{"objID":1644,"componentArray":[{"nam":"ObjectInfo","dat":{"savesWithLevel":{"nam":"bool","dat":true},"id":{"nam":"int","dat":1644},"tags":{"nam":"TagMap","dat":{}},"name":{"nam":"std::string","dat":"CheatTeleport5"},"destroyed":{"nam":"bool","dat":false},"active":{"nam":"bool","dat":true}}},{"nam":"TransformComponent","dat":{"position":{"nam":"vec2","dat":{"x":{"nam":"float","dat":83.2760009765625},"y":{"nam":"float","dat":-19.160001754760743}}},"scale":{"nam":"vec3","dat":{"x":{"nam":"float","dat":1.0},"y":{"nam":"float","dat":1.0},"z":{"nam":"float","dat":1.0}}},"zLayer":{"nam":"float","dat":0.0},"rotation":{"nam":"float","dat":0.0},"parent":{"nam":"GameObject","dat":{"id":{"nam":"int","dat":0}}}}}]},{"objID":1645,"componentArray":[{"nam":"Camera","dat":{"zoom":{"nam":"float","dat":8.756362915039063},"isActiveCam":{"nam":"bool","dat":false}}},{"nam":"ObjectInfo","dat":{"savesWithLevel":{"nam":"bool","dat":true},"id":{"nam":"int","dat":1645},"tags":{"nam":"TagMap","dat":{}},"name":{"nam":"std::string","dat":"Main Camera"},"destroyed":{"nam":"bool","dat":false},"active":{"nam":"bool","dat":true}}},{"nam":"TransformComponent","dat":{"position":{"nam":"vec2","dat":{"x":{"nam":"float","dat":-7.396446704864502},"y":{"nam":"float","dat":1.084037184715271}}},"scale":{"nam":"vec3","dat":{"x":{"nam":"float","dat":0.15000000596046449},"y":{"nam":"float","dat":0.15000000596046449},"z":{"nam":"float","dat":1.0}}},"zLayer":{"nam":"float","dat":0.0},"rotation":{"nam":"float","dat":0.0},"parent":{"nam":"GameObject","dat":{"id":{"nam":"int","dat":0}}}}},{"nam":"ScriptComponent","dat":[{"nam":"LuaScript","dat":{"thisObject":{"nam":"GameObject","dat":{"id":{"nam":"int","dat":1645}}},"resourceID":{"nam":"unsigned long long","dat":2738079508},"vars":{"MIN_ZOOM":{"nam":"double","dat":5.0},"MaxZoom":{"nam":"double","dat":20.0},"dist":{"nam":"double","dat":8.756994247436524},"OFFSET_Y":{"nam":"double","dat":0.5},"ZOOM_SCALE":{"nam":"double","dat":1.0},"LERP_SPEED":{"nam":"double","dat":0.05}}}}]},{"nam":"HierarchyComponent","dat":{}}]},{"objID":1646,"componentArray":[{"nam":"ObjectInfo","dat":{"savesWithLevel":{"nam":"bool","dat":true},"id":{"nam":"int","dat":1646},"tags":{"nam":"TagMap","dat":{}},"name":{"nam":"std::string","dat":"GemCountGUI"},"destroyed":{"nam":"bool","dat":false},"active":{"nam":"bool","dat":true}}},{"nam":"TransformComponent","dat":{"position":{"nam":"vec2","dat":{"x":{"nam":"float","dat":-18.058927536010743},"y":{"nam":"float","dat":3.92287540435791}}},"scale":{"nam":"vec3","dat":{"x":{"nam":"float","dat":1.0},"y":{"nam":"float","dat":1.0},"z":{"nam":"float","dat":1.0}}},"zLayer":{"nam":"float","dat":0.0},"rotation":{"nam":"float","dat":0.0},"parent":{"nam":"GameObject","dat":{"id":{"nam":"int","dat":0}}}}}]},{"objID":1647,"componentArray":[{"nam":"ObjectInfo","dat":{"savesWithLevel":{"nam":"bool","dat":true},"id":{"nam":"int","dat":1647},"tags":{"nam":"TagMap","dat":{}},"name":{"nam":"std::string","dat":"Interact Particles"},"destroyed":{"nam":"bool","dat":false},"active":{"nam":"bool","dat":true}}},{"nam":"TransformComponent","dat":{"position":{"nam":"vec2","dat":{"x":{"nam":"float","dat":1839.1748046875},"y":{"nam":"float","dat":77.14793395996094}}},"scale":{"nam":"vec3","dat":{"x":{"nam":"float","dat":1.0},"y":{"nam":"float","dat":1.0},"z":{"nam":"float","dat":1.0}}},"zLayer":{"nam":"float","dat":99.0},"rotation":{"nam":"float","dat":0.0},"parent":{"nam":"GameObject","dat":{"id":{"nam":"int","dat":0}}}}},{"nam":"ParticleSystem","dat":{"settings":{"nam":"ParticleSettings","dat":{"isLooping":{"nam":"bool","dat":true},"ParticleLifetime":{"nam":"float","dat":1.0},"ParticlesPerEmission":{"nam":"int","dat":1},"EmissionRate":{"nam":"float","dat":0.0010000000474974514},"ScaleOverTime":{"nam":"glm::vec4","dat":{"x":{"nam":"float","dat":0.25},"y":{"nam":"float","dat":0.25},"z":{"nam":"float","dat":0.0},"w":{"nam":"float","dat":0.0}}},"BurstEmission":{"nam":"vec3","dat":{"x":{"nam":"float","dat":0.0},"y":{"nam":"float","dat":0.0},"z":{"nam":"float","dat":0.0}}},"EmissionShape":{"nam":"int","dat":0},"ParticleSpace":{"nam":"int","dat":0},"EmissionShapeScale":{"nam":"vec2","dat":{"x":{"nam":"float","dat":0.0},"y":{"nam":"float","dat":0.0}}},"EmitterLifetime":{"nam":"float","dat":1.0},"ParticleLifetimeVariance":{"nam":"float","dat":0.0},"StartingVelocity":{"nam":"vec2","dat":{"x":{"nam":"float","dat":0.0},"y":{"nam":"float","dat":1.0}}},"StartingVelocityVariance":{"nam":"vec2","dat":{"x":{"nam":"float","dat":0.0},"y":{"nam":"float","dat":0.0}}},"EndColor":{"nam":"glm::vec4","dat":{"x":{"nam":"float","dat":1.0},"y":{"nam":"float","dat":1.0},"z":{"nam":"float","dat":1.0},"w":{"nam":"float","dat":0.0}}},"Acceleration":{"nam":"vec2","dat":{"x":{"nam":"float","dat":0.0},"y":{"nam":"float","dat":0.0}}},"StartRotation":{"nam":"float","dat":0.0},"StartRotationVariation":{"nam":"float","dat":0.0},"RotationRate":{"nam":"float","dat":0.0},"StartColor":{"nam":"glm::vec4","dat":{"x":{"nam":"float","dat":1.0},"y":{"nam":"float","dat":1.0},"z":{"nam":"float","dat":1.0},"w":{"nam":"float","dat":1.0}}},"TextureResourceID":{"nam":"unsigned long long","dat":2704835172},"HasTrail":{"nam":"bool","dat":false},"TrailEmissionRate":{"nam":"float","dat":0.05000000074505806},"TrailLifetime":{"nam":"float","dat":1.0},"TrailScale":{"nam":"vec2","dat":{"x":{"nam":"float","dat":1.0},"y":{"nam":"float","dat":1.0}}},"TrailStartColor":{"nam":"glm::vec4","dat":{"x":{"nam":"float","dat":1.0},"y":{"nam":"float","dat":1.0},"z":{"nam":"float","dat":1.0},"w":{"nam":"float","dat":1.0}}},"TrailEndColor":{"nam":"glm::vec4","dat":{"x":{"nam":"float","dat":1.0},"y":{"nam":"float","dat":1.0},"z":{"nam":"float","dat":1.0},"w":{"nam":"float","dat":1.0}}}}}}}]},{"objID":1648,"componentArray":[{"nam":"ObjectInfo","dat":{"savesWithLevel":{"nam":"bool","dat":true},"id":{"nam":"int","dat":1648},"tags":{"nam":"TagMap","dat":{}},"name":{"nam":"std::string","dat":"Tree2"},"destroyed":{"nam":"bool","dat":false},"active":{"nam":"bool","dat":true}}},{"nam":"TransformComponent","dat":{"position":{"nam":"vec2","dat":{"x":{"nam":"float","dat":-6.336735725402832},"y":{"nam":"float","dat":-15.31224250793457}}},"scale":{"nam":"vec3","dat":{"x":{"nam":"float","dat":5.0},"y":{"nam":"float","dat":6.490000247955322},"z":{"nam":"float","dat":1.0}}},"zLayer":{"nam":"float","dat":-2.0},"rotation":{"nam":"float","dat":0.0},"parent":{"nam":"GameObject","dat":{"id":{"nam":"int","dat":0}}}}},{"nam":"SpriteComponent","dat":{"id":{"nam":"unsigned long long","dat":3227454567},"textureHandler":{"nam":"TextureHandler","dat":{"timer":{"nam":"float","dat":0.0},"isTiling":{"nam":"bool","dat":false},"tileAmount":{"nam":"vec2","dat":{"x":{"nam":"float","dat":1.0},"y":{"nam":"float","dat":1.0}}},"isAnimated":{"nam":"bool","dat":false},"currentFrame":{"nam":"int","dat":0},"id":{"nam":"unsigned long long","dat":3227454567},"fps":{"nam":"float","dat":0.0}}},"color":{"nam":"glm::vec4","dat":{"x":{"nam":"float","dat":1.0},"y":{"nam":"float","dat":1.0},"z":{"nam":"float","dat":1.0},"w":{"nam":"float","dat":1.0}}}}}]},{"objID":1649,"componentArray":[{"nam":"ObjectInfo","dat":{"savesWithLevel":{"nam":"bool","dat":true},"id":{"nam":"int","dat":1649},"tags":{"nam":"TagMap","dat":{}},"name":{"nam":"std::string","dat":"CheatTeleport4"},"destroyed":{"nam":"bool","dat":false},"active":{"nam":"bool","dat":true}}},{"nam":"TransformComponent","dat":{"position":{"nam":"vec2","dat":{"x":{"nam":"float","dat":50.948001861572269},"y":{"nam":"float","dat":-11.858000755310059}}},"scale":{"nam":"vec3","dat":{"x":{"nam":"float","dat":1.0},"y":{"nam":"float","dat":1.0},"z":{"nam":"float","dat":1.0}}},"zLayer":{"nam":"float","dat":0.0},"rotation":{"nam":"float","dat":0.0},"parent":{"nam":"GameObject","dat":{"id":{"nam":"int","dat":0}}}}}]},{"objID":1650,"componentArray":[{"nam":"ObjectInfo","dat":{"savesWithLevel":{"nam":"bool","dat":true},"id":{"nam":"int","dat":1650},"tags":{"nam":"TagMap","dat":{"Enemy":2918293704}},"name":{"nam":"std::string","dat":"NormieShroom"},"destroyed":{"nam":"bool","dat":false},"active":{"nam":"bool","dat":true}}},{"nam":"TransformComponent","dat":{"position":{"nam":"vec2","dat":{"x":{"nam":"float","dat":1734.904541015625},"y":{"nam":"float","dat":-9442419.0}}},"scale":{"nam":"vec3","dat":{"x":{"nam":"float","dat":-1.25},"y":{"nam":"float","dat":2.0},"z":{"nam":"float","dat":1.0}}},"zLayer":{"nam":"float","dat":0.0},"rotation":{"nam":"float","dat":0.0},"parent":{"nam":"GameObject","dat":{"id":{"nam":"int","dat":0}}}}},{"nam":"RigidBodyComponent","dat":{"gravity":{"nam":"vec3","dat":{"x":{"nam":"float","dat":0.0},"y":{"nam":"float","dat":-9.0},"z":{"nam":"float","dat":0.0}}},"acceleration":{"nam":"vec3","dat":{"x":{"nam":"float","dat":0.0},"y":{"nam":"float","dat":0.0},"z":{"nam":"float","dat":0.0}}},"velocity":{"nam":"vec3","dat":{"x":{"nam":"float","dat":-2.0},"y":{"nam":"float","dat":-13035.2373046875},"z":{"nam":"float","dat":0.0}}},"mass":{"nam":"float","dat":0.0}}},{"nam":"DynamicCollider2DComponent","dat":{"colliderData":{"nam":"Collider2D","dat":{"selfElasticity":{"nam":"float","dat":0.0},"colliderShape":{"nam":"int","dat":2},"offset":{"nam":"vec3","dat":{"x":{"nam":"float","dat":0.0},"y":{"nam":"float","dat":0.0},"z":{"nam":"float","dat":0.0}}},"collisionLayer":{"nam":"CollisionLayer","dat":{"layer":{"nam":"int","dat":16}}},"dimensions":{"nam":"vec3","dat":{"x":{"nam":"float","dat":1.25},"y":{"nam":"float","dat":2.0},"z":{"nam":"float","dat":1.0}}},"rotationOffset":{"nam":"float","dat":0.0},"layersCollidedWith":{"nam":"int","dat":0},"collisionType":{"nam":"collisionType","dat":0},"appliedElasticity":{"nam":"float","dat":0.0}}}}},{"nam":"SpriteComponent","dat":{"id":{"nam":"unsigned long long","dat":651912714},"textureHandler":{"nam":"TextureHandler","dat":{"timer":{"nam":"float","dat":0.0},"isTiling":{"nam":"bool","dat":false},"tileAmount":{"nam":"vec2","dat":{"x":{"nam":"float","dat":1.0},"y":{"nam":"float","dat":1.0}}},"isAnimated":{"nam":"bool","dat":false},"currentFrame":{"nam":"int","dat":0},"id":{"nam":"unsigned long long","dat":651912714},"fps":{"nam":"float","dat":0.0}}},"color":{"nam":"glm::vec4","dat":{"x":{"nam":"float","dat":1.0},"y":{"nam":"float","dat":1.0},"z":{"nam":"float","dat":1.0},"w":{"nam":"float","dat":1.0}}}}},{"nam":"ScriptComponent","dat":[{"nam":"LuaScript","dat":{"thisObject":{"nam":"GameObject","dat":{"id":{"nam":"int","dat":1650}}},"resourceID":{"nam":"unsigned long long","dat":1476025226},"vars":{"GROUND_LAYER":{"nam":"double","dat":8.0},"DAMAGE_FLASH_TIME":{"nam":"double","dat":0.1},"damageFlashTimer":{"nam":"double","dat":-681.8032272383571},"speed":{"nam":"double","dat":2.0},"ALLY_PROJECTILE_LAYER":{"nam":"double","dat":32.0},"scared":{"nam":"bool","dat":false},"health":{"nam":"double","dat":10.0},"scaredSpeed":{"nam":"double","dat":3.0},"direction":{"nam":"double","dat":-1.0}}}}]}]},{"objID":1651,"componentArray":[{"nam":"ObjectInfo","dat":{"savesWithLevel":{"nam":"bool","dat":true},"id":{"nam":"int","dat":1651},"tags":{"nam":"TagMap","dat":{"Gem":2089105893}},"name":{"nam":"std::string","dat":"Gem"},"destroyed":{"nam":"bool","dat":false},"active":{"nam":"bool","dat":true}}},{"nam":"TransformComponent","dat":{"position":{"nam":"vec2","dat":{"x":{"nam":"float","dat":10.983772277832032},"y":{"nam":"float","dat":-8.628459930419922}}},"scale":{"nam":"vec3","dat":{"x":{"nam":"float","dat":1.0},"y":{"nam":"float","dat":1.0},"z":{"nam":"float","dat":1.0}}},"zLayer":{"nam":"float","dat":0.0},"rotation":{"nam":"float","dat":0.0},"parent":{"nam":"GameObject","dat":{"id":{"nam":"int","dat":0}}}}},{"nam":"StaticCollider2DComponent","dat":{"colliderData":{"nam":"Collider2D","dat":{"selfElasticity":{"nam":"float","dat":0.0},"colliderShape":{"nam":"int","dat":3},"offset":{"nam":"vec3","dat":{"x":{"nam":"float","dat":0.0},"y":{"nam":"float","dat":0.0},"z":{"nam":"float","dat":0.0}}},"collisionLayer":{"nam":"CollisionLayer","dat":{"layer":{"nam":"int","dat":2}}},"dimensions":{"nam":"vec3","dat":{"x":{"nam":"float","dat":1.0},"y":{"nam":"float","dat":1.0},"z":{"nam":"float","dat":1.0}}},"rotationOffset":{"nam":"float","dat":0.0},"layersCollidedWith":{"nam":"int","dat":0},"collisionType":{"nam":"collisionType","dat":1},"appliedElasticity":{"nam":"float","dat":0.0}}}}},{"nam":"SpriteComponent","dat":{"id":{"nam":"unsigned long long","dat":635731468},"textureHandler":{"nam":"TextureHandler","dat":{"timer":{"nam":"float","dat":0.0},"isTiling":{"nam":"bool","dat":false},"tileAmount":{"nam":"vec2","dat":{"x":{"nam":"float","dat":1.0},"y":{"nam":"float","dat":1.0}}},"isAnimated":{"nam":"bool","dat":false},"currentFrame":{"nam":"int","dat":0},"id":{"nam":"unsigned long long","dat":635731468},"fps":{"nam":"float","dat":0.0}}},"color":{"nam":"glm::vec4","dat":{"x":{"nam":"float","dat":1.0},"y":{"nam":"float","dat":1.0},"z":{"nam":"float","dat":1.0},"w":{"nam":"float","dat":1.0}}}}},{"nam":"ScriptComponent","dat":[{"nam":"LuaScript","dat":{"thisObject":{"nam":"GameObject","dat":{"id":{"nam":"int","dat":1651}}},"resourceID":{"nam":"unsigned long long","dat":3357477322},"vars":{}}}]}]},{"objID":1652,"componentArray":[{"nam":"ObjectInfo","dat":{"savesWithLevel":{"nam":"bool","dat":true},"id":{"nam":"int","dat":1652},"tags":{"nam":"TagMap","dat":{}},"name":{"nam":"std::string","dat":"Goal"},"destroyed":{"nam":"bool","dat":false},"active":{"nam":"bool","dat":true}}},{"nam":"TransformComponent","dat":{"position":{"nam":"vec2","dat":{"x":{"nam":"float","dat":33.51689529418945},"y":{"nam":"float","dat":-12.954233169555664}}},"scale":{"nam":"vec3","dat":{"x":{"nam":"float","dat":5.320000171661377},"y":{"nam":"float","dat":6.490000247955322},"z":{"nam":"float","dat":1.0}}},"zLayer":{"nam":"float","dat":-1.0},"rotation":{"nam":"float","dat":0.0},"parent":{"nam":"GameObject","dat":{"id":{"nam":"int","dat":0}}}}},{"nam":"StaticCollider2DComponent","dat":{"colliderData":{"nam":"Collider2D","dat":{"selfElasticity":{"nam":"float","dat":0.0},"colliderShape":{"nam":"int","dat":8},"offset":{"nam":"vec3","dat":{"x":{"nam":"float","dat":0.0},"y":{"nam":"float","dat":0.0},"z":{"nam":"float","dat":0.0}}},"collisionLayer":{"nam":"CollisionLayer","dat":{"layer":{"nam":"int","dat":2}}},"dimensions":{"nam":"vec3","dat":{"x":{"nam":"float","dat":4.87000036239624},"y":{"nam":"float","dat":6.490000247955322},"z":{"nam":"float","dat":1.0}}},"rotationOffset":{"nam":"float","dat":0.0},"layersCollidedWith":{"nam":"int","dat":0},"collisionType":{"nam":"collisionType","dat":0},"appliedElasticity":{"nam":"float","dat":0.0}}}}},{"nam":"SpriteComponent","dat":{"id":{"nam":"unsigned long long","dat":2780678925},"textureHandler":{"nam":"TextureHandler","dat":{"timer":{"nam":"float","dat":0.0},"isTiling":{"nam":"bool","dat":false},"tileAmount":{"nam":"vec2","dat":{"x":{"nam":"float","dat":1.0},"y":{"nam":"float","dat":1.0}}},"isAnimated":{"nam":"bool","dat":false},"currentFrame":{"nam":"int","dat":0},"id":{"nam":"unsigned long long","dat":2780678925},"fps":{"nam":"float","dat":0.0}}},"color":{"nam":"glm::vec4","dat":{"x":{"nam":"float","dat":1.0},"y":{"nam":"float","dat":0.9999899864196777},"z":{"nam":"float","dat":0.9999899864196777},"w":{"nam":"float","dat":1.0}}}}},{"nam":"ScriptComponent","dat":[{"nam":"LuaScript","dat":{"thisObject":{"nam":"GameObject","dat":{"id":{"nam":"int","dat":1652}}},"resourceID":{"nam":"unsigned long long","dat":475199294},"vars":{"NUM_GEMS_TO_WIN":{"nam":"double","dat":3.0},"WIN_LEVEL":{"nam":"std::string","dat":"YouWinLevel.json"}}}}]}]},{"objID":1653,"componentArray":[{"nam":"ObjectInfo","dat":{"savesWithLevel":{"nam":"bool","dat":true},"id":{"nam":"int","dat":1653},"tags":{"nam":"TagMap","dat":{"Ground":185762651}},"name":{"nam":"std::string","dat":"Ground_Filler2"},"destroyed":{"nam":"bool","dat":false},"active":{"nam":"bool","dat":true}}},{"nam":"TransformComponent","dat":{"position":{"nam":"vec2","dat":{"x":{"nam":"float","dat":-20.362255096435548},"y":{"nam":"float","dat":-14.416754722595215}}},"scale":{"nam":"vec3","dat":{"x":{"nam":"float","dat":8.13690185546875},"y":{"nam":"float","dat":3.2824792861938478},"z":{"nam":"float","dat":1.0}}},"zLayer":{"nam":"float","dat":-1.0},"rotation":{"nam":"float","dat":0.0},"parent":{"nam":"GameObject","dat":{"id":{"nam":"int","dat":0}}}}},{"nam":"SpriteComponent","dat":{"id":{"nam":"unsigned long long","dat":1233411183},"textureHandler":{"nam":"TextureHandler","dat":{"timer":{"nam":"float","dat":0.0},"isTiling":{"nam":"bool","dat":true},"tileAmount":{"nam":"vec2","dat":{"x":{"nam":"float","dat":2.0},"y":{"nam":"float","dat":2.0}}},"isAnimated":{"nam":"bool","dat":false},"currentFrame":{"nam":"int","dat":0},"id":{"nam":"unsigned long long","dat":1233411183},"fps":{"nam":"float","dat":0.0}}},"color":{"nam":"glm::vec4","dat":{"x":{"nam":"float","dat":0.6896551847457886},"y":{"nam":"float","dat":0.6896482706069946},"z":{"nam":"float","dat":0.6896482706069946},"w":{"nam":"float","dat":1.0}}}}}]},{"objID":1654,"componentArray":[{"nam":"ObjectInfo","dat":{"savesWithLevel":{"nam":"bool","dat":true},"id":{"nam":"int","dat":1654},"tags":{"nam":"TagMap","dat":{}},"name":{"nam":"std::string","dat":"Interactive_Destructible"},"destroyed":{"nam":"bool","dat":false},"active":{"nam":"bool","dat":true}}},{"nam":"TransformComponent","dat":{"position":{"nam":"vec2","dat":{"x":{"nam":"float","dat":10.829566955566407},"y":{"nam":"float","dat":-10.389345169067383}}},"scale":{"nam":"vec3","dat":{"x":{"nam":"float","dat":0.5},"y":{"nam":"float","dat":0.5},"z":{"nam":"float","dat":1.0}}},"zLayer":{"nam":"float","dat":0.0},"rotation":{"nam":"float","dat":0.0},"parent":{"nam":"GameObject","dat":{"id":{"nam":"int","dat":0}}}}},{"nam":"StaticCollider2DComponent","dat":{"colliderData":{"nam":"Collider2D","dat":{"selfElasticity":{"nam":"float","dat":0.0},"colliderShape":{"nam":"int","dat":3},"offset":{"nam":"vec3","dat":{"x":{"nam":"float","dat":0.0},"y":{"nam":"float","dat":0.0},"z":{"nam":"float","dat":0.0}}},"collisionLayer":{"nam":"CollisionLayer","dat":{"layer":{"nam":"int","dat":2}}},"dimensions":{"nam":"vec3","dat":{"x":{"nam":"float","dat":0.5},"y":{"nam":"float","dat":0.5},"z":{"nam":"float","dat":1.0}}},"rotationOffset":{"nam":"float","dat":0.0},"layersCollidedWith":{"nam":"int","dat":0},"collisionType":{"nam":"collisionType","dat":1},"appliedElasticity":{"nam":"float","dat":0.0}}}}},{"nam":"SpriteComponent","dat":{"id":{"nam":"unsigned long long","dat":2907720330},"textureHandler":{"nam":"TextureHandler","dat":{"timer":{"nam":"float","dat":0.0},"isTiling":{"nam":"bool","dat":false},"tileAmount":{"nam":"vec2","dat":{"x":{"nam":"float","dat":1.0},"y":{"nam":"float","dat":1.0}}},"isAnimated":{"nam":"bool","dat":false},"currentFrame":{"nam":"int","dat":0},"id":{"nam":"unsigned long long","dat":2907720330},"fps":{"nam":"float","dat":0.0}}},"color":{"nam":"glm::vec4","dat":{"x":{"nam":"float","dat":1.0},"y":{"nam":"float","dat":1.0},"z":{"nam":"float","dat":1.0},"w":{"nam":"float","dat":1.0}}}}}]},{"objID":1655,"componentArray":[{"nam":"ObjectInfo","dat":{"savesWithLevel":{"nam":"bool","dat":true},"id":{"nam":"int","dat":1655},"tags":{"nam":"TagMap","dat":{"Ground":185762651}},"name":{"nam":"std::string","dat":"Ground"},"destroyed":{"nam":"bool","dat":false},"active":{"nam":"bool","dat":true}}},{"nam":"TransformComponent","dat":{"position":{"nam":"vec2","dat":{"x":{"nam":"float","dat":21.4185791015625},"y":{"nam":"float","dat":-10.812326431274414}}},"scale":{"nam":"vec3","dat":{"x":{"nam":"float","dat":13.090106964111329},"y":{"nam":"float","dat":0.5},"z":{"nam":"float","dat":1.0}}},"zLayer":{"nam":"float","dat":0.0},"rotation":{"nam":"float","dat":0.0},"parent":{"nam":"GameObject","dat":{"id":{"nam":"int","dat":0}}}}},{"nam":"StaticCollider2DComponent","dat":{"colliderData":{"nam":"Collider2D","dat":{"selfElasticity":{"nam":"float","dat":0.0},"colliderShape":{"nam":"int","dat":3},"offset":{"nam":"vec3","dat":{"x":{"nam":"float","dat":0.0},"y":{"nam":"float","dat":0.0},"z":{"nam":"float","dat":0.0}}},"collisionLayer":{"nam":"CollisionLayer","dat":{"layer":{"nam":"int","dat":8}}},"dimensions":{"nam":"vec3","dat":{"x":{"nam":"float","dat":13.090106964111329},"y":{"nam":"float","dat":0.5},"z":{"nam":"float","dat":1.0}}},"rotationOffset":{"nam":"float","dat":0.0},"layersCollidedWith":{"nam":"int","dat":0},"collisionType":{"nam":"collisionType","dat":0},"appliedElasticity":{"nam":"float","dat":0.0}}}}},{"nam":"SpriteComponent","dat":{"id":{"nam":"unsigned long long","dat":709983426},"textureHandler":{"nam":"TextureHandler","dat":{"timer":{"nam":"float","dat":0.0},"isTiling":{"nam":"bool","dat":true},"tileAmount":{"nam":"vec2","dat":{"x":{"nam":"float","dat":2.0},"y":{"nam":"float","dat":2.0}}},"isAnimated":{"nam":"bool","dat":false},"currentFrame":{"nam":"int","dat":0},"id":{"nam":"unsigned long long","dat":709983426},"fps":{"nam":"float","dat":0.0}}},"color":{"nam":"glm::vec4","dat":{"x":{"nam":"float","dat":1.0},"y":{"nam":"float","dat":1.0},"z":{"nam":"float","dat":1.0},"w":{"nam":"float","dat":1.0}}}}}]},{"objID":1656,"componentArray":[{"nam":"ObjectInfo","dat":{"savesWithLevel":{"nam":"bool","dat":true},"id":{"nam":"int","dat":1656},"tags":{"nam":"TagMap","dat":{"Ground":185762651}},"name":{"nam":"std::string","dat":"Ground"},"destroyed":{"nam":"bool","dat":false},"active":{"nam":"bool","dat":true}}},{"nam":"TransformComponent","dat":{"position":{"nam":"vec2","dat":{"x":{"nam":"float","dat":-22.659564971923829},"y":{"nam":"float","dat":-10.71469783782959}}},"scale":{"nam":"vec3","dat":{"x":{"nam":"float","dat":13.001689910888672},"y":{"nam":"float","dat":0.894658088684082},"z":{"nam":"float","dat":1.0}}},"zLayer":{"nam":"float","dat":1.0},"rotation":{"nam":"float","dat":0.0},"parent":{"nam":"GameObject","dat":{"id":{"nam":"int","dat":0}}}}},{"nam":"StaticCollider2DComponent","dat":{"colliderData":{"nam":"Collider2D","dat":{"selfElasticity":{"nam":"float","dat":0.0},"colliderShape":{"nam":"int","dat":3},"offset":{"nam":"vec3","dat":{"x":{"nam":"float","dat":0.0},"y":{"nam":"float","dat":0.0},"z":{"nam":"float","dat":0.0}}},"collisionLayer":{"nam":"CollisionLayer","dat":{"layer":{"nam":"int","dat":8}}},"dimensions":{"nam":"vec3","dat":{"x":{"nam":"float","dat":13.001689910888672},"y":{"nam":"float","dat":1.0},"z":{"nam":"float","dat":1.0}}},"rotationOffset":{"nam":"float","dat":0.0},"layersCollidedWith":{"nam":"int","dat":0},"collisionType":{"nam":"collisionType","dat":0},"appliedElasticity":{"nam":"float","dat":0.0}}}}},{"nam":"SpriteComponent","dat":{"id":{"nam":"unsigned long long","dat":1233411183},"textureHandler":{"nam":"TextureHandler","dat":{"timer":{"nam":"float","dat":0.0},"isTiling":{"nam":"bool","dat":true},"tileAmount":{"nam":"vec2","dat":{"x":{"nam":"float","dat":2.0},"y":{"nam":"float","dat":2.0}}},"isAnimated":{"nam":"bool","dat":false},"currentFrame":{"nam":"int","dat":0},"id":{"nam":"unsigned long long","dat":1233411183},"fps":{"nam":"float","dat":0.0}}},"color":{"nam":"glm::vec4","dat":{"x":{"nam":"float","dat":1.0},"y":{"nam":"float","dat":0.9999899864196777},"z":{"nam":"float","dat":0.9999899864196777},"w":{"nam":"float","dat":1.0}}}}}]},{"objID":1657,"componentArray":[{"nam":"ObjectInfo","dat":{"savesWithLevel":{"nam":"bool","dat":true},"id":{"nam":"int","dat":1657},"tags":{"nam":"TagMap","dat":{"Ground":185762651}},"name":{"nam":"std::string","dat":"Background_Cave"},"destroyed":{"nam":"bool","dat":false},"active":{"nam":"bool","dat":true}}},{"nam":"TransformComponent","dat":{"position":{"nam":"vec2","dat":{"x":{"nam":"float","dat":-17.2928466796875},"y":{"nam":"float","dat":-21.798608779907228}}},"scale":{"nam":"vec3","dat":{"x":{"nam":"float","dat":19.109745025634767},"y":{"nam":"float","dat":9.109477996826172},"z":{"nam":"float","dat":1.0}}},"zLayer":{"nam":"float","dat":-5.0},"rotation":{"nam":"float","dat":0.0},"parent":{"nam":"GameObject","dat":{"id":{"nam":"int","dat":0}}}}},{"nam":"SpriteComponent","dat":{"id":{"nam":"unsigned long long","dat":260529048},"textureHandler":{"nam":"TextureHandler","dat":{"timer":{"nam":"float","dat":0.0},"isTiling":{"nam":"bool","dat":true},"tileAmount":{"nam":"vec2","dat":{"x":{"nam":"float","dat":2.0},"y":{"nam":"float","dat":2.0}}},"isAnimated":{"nam":"bool","dat":false},"currentFrame":{"nam":"int","dat":0},"id":{"nam":"unsigned long long","dat":260529048},"fps":{"nam":"float","dat":0.0}}},"color":{"nam":"glm::vec4","dat":{"x":{"nam":"float","dat":0.8068965673446655},"y":{"nam":"float","dat":0.5715848803520203},"z":{"nam":"float","dat":0.18920333683490754},"w":{"nam":"float","dat":1.0}}}}}]},{"objID":1658,"componentArray":[{"nam":"ObjectInfo","dat":{"savesWithLevel":{"nam":"bool","dat":true},"id":{"nam":"int","dat":1658},"tags":{"nam":"TagMap","dat":{"Ground":185762651}},"name":{"nam":"std::string","dat":"Ground"},"destroyed":{"nam":"bool","dat":false},"active":{"nam":"bool","dat":true}}},{"nam":"TransformComponent","dat":{"position":{"nam":"vec2","dat":{"x":{"nam":"float","dat":-13.772610664367676},"y":{"nam":"float","dat":-9.526568412780762}}},"scale":{"nam":"vec3","dat":{"x":{"nam":"float","dat":1.6625094413757325},"y":{"nam":"float","dat":0.25},"z":{"nam":"float","dat":1.0}}},"zLayer":{"nam":"float","dat":0.0},"rotation":{"nam":"float","dat":0.0},"parent":{"nam":"GameObject","dat":{"id":{"nam":"int","dat":0}}}}},{"nam":"StaticCollider2DComponent","dat":{"colliderData":{"nam":"Collider2D","dat":{"selfElasticity":{"nam":"float","dat":0.0},"colliderShape":{"nam":"int","dat":3},"offset":{"nam":"vec3","dat":{"x":{"nam":"float","dat":0.0},"y":{"nam":"float","dat":0.0},"z":{"nam":"float","dat":0.0}}},"collisionLayer":{"nam":"CollisionLayer","dat":{"layer":{"nam":"int","dat":8}}},"dimensions":{"nam":"vec3","dat":{"x":{"nam":"float","dat":1.6625094413757325},"y":{"nam":"float","dat":0.25},"z":{"nam":"float","dat":1.0}}},"rotationOffset":{"nam":"float","dat":0.0},"layersCollidedWith":{"nam":"int","dat":0},"collisionType":{"nam":"collisionType","dat":0},"appliedElasticity":{"nam":"float","dat":0.0}}}}},{"nam":"SpriteComponent","dat":{"id":{"nam":"unsigned long long","dat":4046731729},"textureHandler":{"nam":"TextureHandler","dat":{"timer":{"nam":"float","dat":0.0},"isTiling":{"nam":"bool","dat":true},"tileAmount":{"nam":"vec2","dat":{"x":{"nam":"float","dat":2.0},"y":{"nam":"float","dat":2.0}}},"isAnimated":{"nam":"bool","dat":false},"currentFrame":{"nam":"int","dat":0},"id":{"nam":"unsigned long long","dat":4046731729},"fps":{"nam":"float","dat":0.0}}},"color":{"nam":"glm::vec4","dat":{"x":{"nam":"float","dat":1.0},"y":{"nam":"float","dat":1.0},"z":{"nam":"float","dat":1.0},"w":{"nam":"float","dat":1.0}}}}}]},{"objID":1659,"componentArray":[{"nam":"ObjectInfo","dat":{"savesWithLevel":{"nam":"bool","dat":true},"id":{"nam":"int","dat":1659},"tags":{"nam":"TagMap","dat":{}},"name":{"nam":"std::string","dat":"Ground_Filler1"},"destroyed":{"nam":"bool","dat":false},"active":{"nam":"bool","dat":true}}},{"nam":"TransformComponent","dat":{"position":{"nam":"vec2","dat":{"x":{"nam":"float","dat":-10.649672508239746},"y":{"nam":"float","dat":-10.871554374694825}}},"scale":{"nam":"vec3","dat":{"x":{"nam":"float","dat":2.0},"y":{"nam":"float","dat":6.0},"z":{"nam":"float","dat":1.0}}},"zLayer":{"nam":"float","dat":0.0},"rotation":{"nam":"float","dat":0.0},"parent":{"nam":"GameObject","dat":{"id":{"nam":"int","dat":0}}}}},{"nam":"SpriteComponent","dat":{"id":{"nam":"unsigned long long","dat":1233411183},"textureHandler":{"nam":"TextureHandler","dat":{"timer":{"nam":"float","dat":0.0},"isTiling":{"nam":"bool","dat":true},"tileAmount":{"nam":"vec2","dat":{"x":{"nam":"float","dat":1.0},"y":{"nam":"float","dat":1.0}}},"isAnimated":{"nam":"bool","dat":false},"currentFrame":{"nam":"int","dat":0},"id":{"nam":"unsigned long long","dat":1233411183},"fps":{"nam":"float","dat":0.0}}},"color":{"nam":"glm::vec4","dat":{"x":{"nam":"float","dat":1.0},"y":{"nam":"float","dat":1.0},"z":{"nam":"float","dat":1.0},"w":{"nam":"float","dat":1.0}}}}}]},{"objID":1660,"componentArray":[{"nam":"ObjectInfo","dat":{"savesWithLevel":{"nam":"bool","dat":true},"id":{"nam":"int","dat":1660},"tags":{"nam":"TagMap","dat":{"Ground":185762651}},"name":{"nam":"std::string","dat":"Ground"},"destroyed":{"nam":"bool","dat":false},"active":{"nam":"bool","dat":true}}},{"nam":"TransformComponent","dat":{"position":{"nam":"vec2","dat":{"x":{"nam":"float","dat":-13.821949005126954},"y":{"nam":"float","dat":-10.888566017150879}}},"scale":{"nam":"vec3","dat":{"x":{"nam":"float","dat":2.565624237060547},"y":{"nam":"float","dat":0.5},"z":{"nam":"float","dat":1.0}}},"zLayer":{"nam":"float","dat":0.0},"rotation":{"nam":"float","dat":0.0},"parent":{"nam":"GameObject","dat":{"id":{"nam":"int","dat":0}}}}},{"nam":"StaticCollider2DComponent","dat":{"colliderData":{"nam":"Collider2D","dat":{"selfElasticity":{"nam":"float","dat":0.0},"colliderShape":{"nam":"int","dat":3},"offset":{"nam":"vec3","dat":{"x":{"nam":"float","dat":0.0},"y":{"nam":"float","dat":0.0},"z":{"nam":"float","dat":0.0}}},"collisionLayer":{"nam":"CollisionLayer","dat":{"layer":{"nam":"int","dat":8}}},"dimensions":{"nam":"vec3","dat":{"x":{"nam":"float","dat":2.565624237060547},"y":{"nam":"float","dat":0.5},"z":{"nam":"float","dat":1.0}}},"rotationOffset":{"nam":"float","dat":0.0},"layersCollidedWith":{"nam":"int","dat":0},"collisionType":{"nam":"collisionType","dat":0},"appliedElasticity":{"nam":"float","dat":0.0}}}}},{"nam":"SpriteComponent","dat":{"id":{"nam":"unsigned long long","dat":709983426},"textureHandler":{"nam":"TextureHandler","dat":{"timer":{"nam":"float","dat":0.0},"isTiling":{"nam":"bool","dat":true},"tileAmount":{"nam":"vec2","dat":{"x":{"nam":"float","dat":2.0},"y":{"nam":"float","dat":2.0}}},"isAnimated":{"nam":"bool","dat":false},"currentFrame":{"nam":"int","dat":0},"id":{"nam":"unsigned long long","dat":709983426},"fps":{"nam":"float","dat":0.0}}},"color":{"nam":"glm::vec4","dat":{"x":{"nam":"float","dat":1.0},"y":{"nam":"float","dat":1.0},"z":{"nam":"float","dat":1.0},"w":{"nam":"float","dat":1.0}}}}}]},{"objID":1661,"componentArray":[{"nam":"ObjectInfo","dat":{"savesWithLevel":{"nam":"bool","dat":true},"id":{"nam":"int","dat":1661},"tags":{"nam":"TagMap","dat":{"Ground":185762651}},"name":{"nam":"std::string","dat":"Ground"},"destroyed":{"nam":"bool","dat":false},"active":{"nam":"bool","dat":true}}},{"nam":"TransformComponent","dat":{"position":{"nam":"vec2","dat":{"x":{"nam":"float","dat":27.615821838378908},"y":{"nam":"float","dat":-12.463711738586426}}},"scale":{"nam":"vec3","dat":{"x":{"nam":"float","dat":0.5},"y":{"nam":"float","dat":3.0},"z":{"nam":"float","dat":1.0}}},"zLayer":{"nam":"float","dat":0.0},"rotation":{"nam":"float","dat":0.0},"parent":{"nam":"GameObject","dat":{"id":{"nam":"int","dat":0}}}}},{"nam":"StaticCollider2DComponent","dat":{"colliderData":{"nam":"Collider2D","dat":{"selfElasticity":{"nam":"float","dat":0.0},"colliderShape":{"nam":"int","dat":3},"offset":{"nam":"vec3","dat":{"x":{"nam":"float","dat":0.0},"y":{"nam":"float","dat":0.0},"z":{"nam":"float","dat":0.0}}},"collisionLayer":{"nam":"CollisionLayer","dat":{"layer":{"nam":"int","dat":8}}},"dimensions":{"nam":"vec3","dat":{"x":{"nam":"float","dat":0.5},"y":{"nam":"float","dat":3.0},"z":{"nam":"float","dat":1.0}}},"rotationOffset":{"nam":"float","dat":0.0},"layersCollidedWith":{"nam":"int","dat":0},"collisionType":{"nam":"collisionType","dat":0},"appliedElasticity":{"nam":"float","dat":0.0}}}}},{"nam":"SpriteComponent","dat":{"id":{"nam":"unsigned long long","dat":709983426},"textureHandler":{"nam":"TextureHandler","dat":{"timer":{"nam":"float","dat":0.0},"isTiling":{"nam":"bool","dat":true},"tileAmount":{"nam":"vec2","dat":{"x":{"nam":"float","dat":2.0},"y":{"nam":"float","dat":2.0}}},"isAnimated":{"nam":"bool","dat":false},"currentFrame":{"nam":"int","dat":0},"id":{"nam":"unsigned long long","dat":709983426},"fps":{"nam":"float","dat":0.0}}},"color":{"nam":"glm::vec4","dat":{"x":{"nam":"float","dat":1.0},"y":{"nam":"float","dat":1.0},"z":{"nam":"float","dat":1.0},"w":{"nam":"float","dat":1.0}}}}}]},{"objID":1662,"componentArray":[{"nam":"ObjectInfo","dat":{"savesWithLevel":{"nam":"bool","dat":true},"id":{"nam":"int","dat":1662},"tags":{"nam":"TagMap","dat":{"Ground":185762651}},"name":{"nam":"std::string","dat":"Ground"},"destroyed":{"nam":"bool","dat":false},"active":{"nam":"bool","dat":true}}},{"nam":"TransformComponent","dat":{"position":{"nam":"vec2","dat":{"x":{"nam":"float","dat":-20.170482635498048},"y":{"nam":"float","dat":-7.752164840698242}}},"scale":{"nam":"vec3","dat":{"x":{"nam":"float","dat":9.905972480773926},"y":{"nam":"float","dat":0.5},"z":{"nam":"float","dat":1.0}}},"zLayer":{"nam":"float","dat":0.0},"rotation":{"nam":"float","dat":0.0},"parent":{"nam":"GameObject","dat":{"id":{"nam":"int","dat":0}}}}},{"nam":"StaticCollider2DComponent","dat":{"colliderData":{"nam":"Collider2D","dat":{"selfElasticity":{"nam":"float","dat":0.0},"colliderShape":{"nam":"int","dat":3},"offset":{"nam":"vec3","dat":{"x":{"nam":"float","dat":0.0},"y":{"nam":"float","dat":0.0},"z":{"nam":"float","dat":0.0}}},"collisionLayer":{"nam":"CollisionLayer","dat":{"layer":{"nam":"int","dat":8}}},"dimensions":{"nam":"vec3","dat":{"x":{"nam":"float","dat":9.905972480773926},"y":{"nam":"float","dat":0.5},"z":{"nam":"float","dat":1.0}}},"rotationOffset":{"nam":"float","dat":0.0},"layersCollidedWith":{"nam":"int","dat":0},"collisionType":{"nam":"collisionType","dat":0},"appliedElasticity":{"nam":"float","dat":0.0}}}}},{"nam":"SpriteComponent","dat":{"id":{"nam":"unsigned long long","dat":4046731729},"textureHandler":{"nam":"TextureHandler","dat":{"timer":{"nam":"float","dat":0.0},"isTiling":{"nam":"bool","dat":true},"tileAmount":{"nam":"vec2","dat":{"x":{"nam":"float","dat":2.0},"y":{"nam":"float","dat":2.0}}},"isAnimated":{"nam":"bool","dat":false},"currentFrame":{"nam":"int","dat":0},"id":{"nam":"unsigned long long","dat":4046731729},"fps":{"nam":"float","dat":0.0}}},"color":{"nam":"glm::vec4","dat":{"x":{"nam":"float","dat":1.0},"y":{"nam":"float","dat":1.0},"z":{"nam":"float","dat":1.0},"w":{"nam":"float","dat":1.0}}}}}]},{"objID":1663,"componentArray":[{"nam":"ObjectInfo","dat":{"savesWithLevel":{"nam":"bool","dat":true},"id":{"nam":"int","dat":1663},"tags":{"nam":"TagMap","dat":{}},"name":{"nam":"std::string","dat":"PlayerSpawner"},"destroyed":{"nam":"bool","dat":false},"active":{"nam":"bool","dat":true}}},{"nam":"TransformComponent","dat":{"position":{"nam":"vec2","dat":{"x":{"nam":"float","dat":-11.581348419189454},"y":{"nam":"float","dat":0.8208189010620117}}},"scale":{"nam":"vec3","dat":{"x":{"nam":"float","dat":1.0},"y":{"nam":"float","dat":1.0},"z":{"nam":"float","dat":1.0}}},"zLayer":{"nam":"float","dat":0.0},"rotation":{"nam":"float","dat":0.0},"parent":{"nam":"GameObject","dat":{"id":{"nam":"int","dat":0}}}}},{"nam":"ScriptComponent","dat":[{"nam":"LuaScript","dat":{"thisObject":{"nam":"GameObject","dat":{"id":{"nam":"int","dat":1663}}},"resourceID":{"nam":"unsigned long long","dat":2284044530},"vars":{"SPAWNER_WIDTH":{"nam":"double","dat":5.0}}}}]}]},{"objID":1664,"componentArray":[{"nam":"ObjectInfo","dat":{"savesWithLevel":{"nam":"bool","dat":true},"id":{"nam":"int","dat":1664},"tags":{"nam":"TagMap","dat":{}},"name":{"nam":"std::string","dat":"TimerBar"},"destroyed":{"nam":"bool","dat":false},"active":{"nam":"bool","dat":true}}},{"nam":"TransformComponent","dat":{"position":{"nam":"vec2","dat":{"x":{"nam":"float","dat":-1.6172471046447755},"y":{"nam":"float","dat":5.462218761444092}}},"scale":{"nam":"vec3","dat":{"x":{"nam":"float","dat":5.691636085510254},"y":{"nam":"float","dat":0.43781813979148867},"z":{"nam":"float","dat":1.0}}},"zLayer":{"nam":"float","dat":1000.0},"rotation":{"nam":"float","dat":0.0},"parent":{"nam":"GameObject","dat":{"id":{"nam":"int","dat":1645}}}}},{"nam":"SpriteComponent","dat":{"id":{"nam":"unsigned long long","dat":2225379469},"textureHandler":{"nam":"TextureHandler","dat":{"timer":{"nam":"float","dat":0.0},"isTiling":{"nam":"bool","dat":false},"tileAmount":{"nam":"vec2","dat":{"x":{"nam":"float","dat":1.0},"y":{"nam":"float","dat":1.0}}},"isAnimated":{"nam":"bool","dat":false},"currentFrame":{"nam":"int","dat":0},"id":{"nam":"unsigned long long","dat":2225379469},"fps":{"nam":"float","dat":0.0}}},"color":{"nam":"glm::vec4","dat":{"x":{"nam":"float","dat":1.0},"y":{"nam":"float","dat":1.0},"z":{"nam":"float","dat":1.0},"w":{"nam":"float","dat":1.0}}}}},{"nam":"ScriptComponent","dat":[{"nam":"LuaScript","dat":{"thisObject":{"nam":"GameObject","dat":{"id":{"nam":"int","dat":1664}}},"resourceID":{"nam":"unsigned long long","dat":1665779242},"vars":{"star_2":{"nam":"double","dat":20.0},"maxTime":{"nam":"double","dat":80.0},"STAR_SPRITE_ACTIVE":{"nam":"std::string","dat":"Sticker_ChallengeGem.png"},"STAR_COUNT":{"nam":"double","dat":3.0},"starHeight":{"nam":"double","dat":1.0},"startingTime":{"nam":"double","dat":60.0},"star_1":{"nam":"double","dat":10.0},"resetTimer":{"nam":"bool","dat":false},"timer":{"nam":"double","dat":0.0},"star_3":{"nam":"double","dat":40.0},"STAR_SPRITE_MISSED":{"nam":"std::string","dat":"Sticker_Gem.png"}}}},{"nam":"LuaScript","dat":{"thisObject":{"nam":"GameObject","dat":{"id":{"nam":"int","dat":1664}}},"resourceID":{"nam":"unsigned long long","dat":189875031},"vars":{"offset_y":{"nam":"double","dat":2.5},"scale_y":{"nam":"double","dat":0.25},"offset_x":{"nam":"double","dat":3.299999952316284},"scale_x":{"nam":"double","dat":3.25},"SCALE_FACTOR":{"nam":"double","dat":5.0}}}}]},{"nam":"HierarchyComponent","dat":{}}]},{"objID":1665,"componentArray":[{"nam":"ObjectInfo","dat":{"savesWithLevel":{"nam":"bool","dat":true},"id":{"nam":"int","dat":1665},"tags":{"nam":"TagMap","dat":{}},"name":{"nam":"std::string","dat":"Projectile_Red_onYellow"},"destroyed":{"nam":"bool","dat":false},"active":{"nam":"bool","dat":true}}},{"nam":"TransformComponent","dat":{"position":{"nam":"vec2","dat":{"x":{"nam":"float","dat":-9.331348419189454},"y":{"nam":"float","dat":0.5708189010620117}}},"scale":{"nam":"vec3","dat":{"x":{"nam":"float","dat":2.0},"y":{"nam":"float","dat":2.0},"z":{"nam":"float","dat":1.0}}},"zLayer":{"nam":"float","dat":0.0},"rotation":{"nam":"float","dat":0.0},"parent":{"nam":"GameObject","dat":{"id":{"nam":"int","dat":0}}}}},{"nam":"RigidBodyComponent","dat":{"gravity":{"nam":"vec3","dat":{"x":{"nam":"float","dat":0.0},"y":{"nam":"float","dat":0.0},"z":{"nam":"float","dat":0.0}}},"acceleration":{"nam":"vec3","dat":{"x":{"nam":"float","dat":0.0},"y":{"nam":"float","dat":0.0},"z":{"nam":"float","dat":0.0}}},"velocity":{"nam":"vec3","dat":{"x":{"nam":"float","dat":0.0},"y":{"nam":"float","dat":0.0},"z":{"nam":"float","dat":0.0}}},"mass":{"nam":"float","dat":0.0}}},{"nam":"DynamicCollider2DComponent","dat":{"colliderData":{"nam":"Collider2D","dat":{"selfElasticity":{"nam":"float","dat":0.0},"colliderShape":{"nam":"int","dat":2},"offset":{"nam":"vec3","dat":{"x":{"nam":"float","dat":-0.25},"y":{"nam":"float","dat":0.0},"z":{"nam":"float","dat":0.0}}},"collisionLayer":{"nam":"CollisionLayer","dat":{"layer":{"nam":"int","dat":32}}},"dimensions":{"nam":"vec3","dat":{"x":{"nam":"float","dat":1.5},"y":{"nam":"float","dat":1.0},"z":{"nam":"float","dat":1.0}}},"rotationOffset":{"nam":"float","dat":0.0},"layersCollidedWith":{"nam":"int","dat":8},"collisionType":{"nam":"collisionType","dat":1},"appliedElasticity":{"nam":"float","dat":0.0}}}}},{"nam":"SpriteComponent","dat":{"id":{"nam":"unsigned long long","dat":402368039},"textureHandler":{"nam":"TextureHandler","dat":{"timer":{"nam":"float","dat":0.0833740234375},"isTiling":{"nam":"bool","dat":false},"tileAmount":{"nam":"vec2","dat":{"x":{"nam":"float","dat":1.0},"y":{"nam":"float","dat":1.0}}},"isAnimated":{"nam":"bool","dat":true},"currentFrame":{"nam":"int","dat":0},"id":{"nam":"unsigned long long","dat":402368039},"fps":{"nam":"float","dat":8.0}}},"color":{"nam":"glm::vec4","dat":{"x":{"nam":"float","dat":1.0},"y":{"nam":"float","dat":1.0},"z":{"nam":"float","dat":1.0},"w":{"nam":"float","dat":1.0}}}}},{"nam":"ScriptComponent","dat":[{"nam":"LuaScript","dat":{"thisObject":{"nam":"GameObject","dat":{"id":{"nam":"int","dat":1665}}},"resourceID":{"nam":"unsigned long long","dat":797020738},"vars":{"offsetY":{"nam":"double","dat":-0.25},"isMelee":{"nam":"bool","dat":true},"cooldownTime":{"nam":"double","dat":0.25},"speed":{"nam":"double","dat":0.0},"parented":{"nam":"bool","dat":true},"life":{"nam":"double","dat":0.25},"offsetX":{"nam":"double","dat":1.0}}}}]}]},{"objID":1666,"componentArray":[{"nam":"ObjectInfo","dat":{"savesWithLevel":{"nam":"bool","dat":true},"id":{"nam":"int","dat":1666},"tags":{"nam":"TagMap","dat":{}},"name":{"nam":"std::string","dat":"Scale"},"destroyed":{"nam":"bool","dat":false},"active":{"nam":"bool","dat":true}}},{"nam":"TransformComponent","dat":{"position":{"nam":"vec2","dat":{"x":{"nam":"float","dat":-3.7419724464416506},"y":{"nam":"float","dat":4.596336364746094}}},"scale":{"nam":"vec3","dat":{"x":{"nam":"float","dat":1.0},"y":{"nam":"float","dat":1.0},"z":{"nam":"float","dat":1.0}}},"zLayer":{"nam":"float","dat":0.0},"rotation":{"nam":"float","dat":0.0},"parent":{"nam":"GameObject","dat":{"id":{"nam":"int","dat":0}}}}},{"nam":"ScriptComponent","dat":[{"nam":"LuaScript","dat":{"thisObject":{"nam":"GameObject","dat":{"id":{"nam":"int","dat":1666}}},"resourceID":{"nam":"unsigned long long","dat":1159609835},"vars":{"correctionFactor":{"nam":"double","dat":-1.0},"currentVelocity":{"nam":"double","dat":8.143514725239056e-8},"maxSpeed":{"nam":"double","dat":3.0},"frictionFactor":{"nam":"double","dat":0.8},"pulleyStartOffsetRight_x":{"nam":"double","dat":3.0},"accelerationPerGnome":{"nam":"double","dat":0.5},"startingLeftRopeLength":{"nam":"double","dat":3.0},"pulleyStartOffsetLeft_x":{"nam":"double","dat":-3.0},"pulleyStartOffsetRight_y":{"nam":"double","dat":0.0},"platformLeftWidth":{"nam":"double","dat":2.0},"leftRopeLength":{"nam":"double","dat":3.000000724458487},"pulleyStartOffsetLeft_y":{"nam":"double","dat":0.0},"platformRightWidth":{"nam":"double","dat":2.0},"averageRopeLength":{"nam":"double","dat":3.0}}}}]},{"nam":"HierarchyComponent","dat":{}}]}]}]}