{"objID":1395,"componentArray":[{"nam":"ObjectInfo","dat":{"savesWithLevel":{"nam":"bool","dat":false},"id":{"nam":"int","dat":1395},"tags":{"nam":"TagMap","dat":{}},"name":{"nam":"std::string","dat":"Projectile_Red_onYellow"},"destroyed":{"nam":"bool","dat":false},"active":{"nam":"bool","dat":true}}},{"nam":"TransformComponent","dat":{"position":{"nam":"vec2","dat":{"x":{"nam":"float","dat":-99.16644287109375},"y":{"nam":"float","dat":-3.991675853729248}}},"scale":{"nam":"vec3","dat":{"x":{"nam":"float","dat":2.0},"y":{"nam":"float","dat":2.0},"z":{"nam":"float","dat":1.0}}},"zLayer":{"nam":"float","dat":0.0},"rotation":{"nam":"float","dat":0.0},"parent":{"nam":"GameObject","dat":{"id":{"nam":"int","dat":1146}}}}},{"nam":"RigidBodyComponent","dat":{"gravity":{"nam":"vec3","dat":{"x":{"nam":"float","dat":0.0},"y":{"nam":"float","dat":0.0},"z":{"nam":"float","dat":0.0}}},"acceleration":{"nam":"vec3","dat":{"x":{"nam":"float","dat":0.0},"y":{"nam":"float","dat":0.0},"z":{"nam":"float","dat":0.0}}},"velocity":{"nam":"vec3","dat":{"x":{"nam":"float","dat":0.0},"y":{"nam":"float","dat":0.0},"z":{"nam":"float","dat":0.0}}},"mass":{"nam":"float","dat":0.0}}},{"nam":"DynamicCollider2DComponent","dat":{"colliderData":{"nam":"Collider2D","dat":{"selfElasticity":{"nam":"float","dat":0.0},"colliderShape":{"nam":"int","dat":2},"offset":{"nam":"vec3","dat":{"x":{"nam":"float","dat":0.5},"y":{"nam":"float","dat":0.0},"z":{"nam":"float","dat":0.0}}},"collisionLayer":{"nam":"CollisionLayer","dat":{"layer":{"nam":"int","dat":32}}},"dimensions":{"nam":"vec3","dat":{"x":{"nam":"float","dat":1.0},"y":{"nam":"float","dat":2.0},"z":{"nam":"float","dat":1.0}}},"rotationOffset":{"nam":"float","dat":0.0},"layersCollidedWith":{"nam":"int","dat":0},"collisionType":{"nam":"collisionType","dat":1},"appliedElasticity":{"nam":"float","dat":0.0}}}}},{"nam":"SpriteComponent","dat":{"id":{"nam":"unsigned long long","dat":1741780358},"textureHandler":{"nam":"TextureHandler","dat":{"timer":{"nam":"float","dat":0.13198143243789674},"isTiling":{"nam":"bool","dat":false},"tileAmount":{"nam":"vec2","dat":{"x":{"nam":"float","dat":1.0},"y":{"nam":"float","dat":1.0}}},"isAnimated":{"nam":"bool","dat":true},"currentFrame":{"nam":"int","dat":0},"id":{"nam":"unsigned long long","dat":1741780358},"fps":{"nam":"float","dat":7.0}}},"color":{"nam":"glm::vec4","dat":{"x":{"nam":"float","dat":1.0},"y":{"nam":"float","dat":1.0},"z":{"nam":"float","dat":1.0},"w":{"nam":"float","dat":1.0}}}}},{"nam":"ScriptComponent","dat":[{"nam":"LuaScript","dat":{"thisObject":{"nam":"GameObject","dat":{"id":{"nam":"int","dat":1395}}},"resourceID":{"nam":"unsigned long long","dat":797020738},"vars":{"parented":{"nam":"bool","dat":true},"life":{"nam":"double","dat":0.239999994635582},"isMelee":{"nam":"bool","dat":true},"offsetY":{"nam":"double","dat":0.125},"offsetX":{"nam":"double","dat":1.0},"cooldownTime":{"nam":"double","dat":0.30000001192092898},"speed":{"nam":"double","dat":0.0},"hitParticle":{"nam":"std::string","dat":"assets/prefabs/Particles_Red_Hit.json"},"damage":{"nam":"double","dat":2.5},"isRight":{"nam":"bool","dat":true}}}},{"nam":"LuaScript","dat":{"thisObject":{"nam":"GameObject","dat":{"id":{"nam":"int","dat":1395}}},"resourceID":{"nam":"unsigned long long","dat":2392297171},"vars":{"SPAWN_OFFSET_Y":{"nam":"double","dat":-0.5},"ParticlePrefab":{"nam":"std::string","dat":"Particles_Red_Standard.json"},"SPAWN_OFFSET_X":{"nam":"double","dat":0.25}}}}]},{"nam":"HierarchyComponent","dat":{}}]}